package com.android.server;

import android.content.ComponentName;
import android.content.pm.FeatureInfo;
import android.os.Build;
import android.os.Build.VERSION;
import android.os.Environment;
import android.os.Process;
import android.text.TextUtils;
import android.util.ArrayMap;
import android.util.ArraySet;
import android.util.Slog;
import android.util.SparseArray;
import com.android.internal.util.ArrayUtils;
import com.android.internal.util.XmlUtils;
import java.io.File;
import java.io.IOException;
import java.util.Collections;
import java.util.List;
import java.util.Map;
import org.xmlpull.v1.XmlPullParser;
import org.xmlpull.v1.XmlPullParserException;

public class SystemConfig
{
  private static final int ALLOW_ALL = -1;
  private static final int ALLOW_APP_CONFIGS = 8;
  private static final int ALLOW_FEATURES = 1;
  private static final int ALLOW_HIDDENAPI_WHITELISTING = 64;
  private static final int ALLOW_LIBS = 2;
  private static final int ALLOW_OEM_PERMISSIONS = 32;
  private static final int ALLOW_PERMISSIONS = 4;
  private static final int ALLOW_PRIVAPP_PERMISSIONS = 16;
  static final String TAG = "SystemConfig";
  static SystemConfig sInstance;
  final ArraySet<String> mAllowImplicitBroadcasts = new ArraySet();
  final ArraySet<String> mAllowInDataUsageSave = new ArraySet();
  final ArraySet<String> mAllowInPowerSave = new ArraySet();
  final ArraySet<String> mAllowInPowerSaveExceptIdle = new ArraySet();
  final ArraySet<String> mAllowUnthrottledLocation = new ArraySet();
  final ArrayMap<String, FeatureInfo> mAvailableFeatures = new ArrayMap();
  final ArraySet<ComponentName> mBackupTransportWhitelist = new ArraySet();
  final ArraySet<ComponentName> mDefaultVrComponents = new ArraySet();
  final ArraySet<String> mDisabledUntilUsedPreinstalledCarrierApps = new ArraySet();
  final ArrayMap<String, List<String>> mDisabledUntilUsedPreinstalledCarrierAssociatedApps = new ArrayMap();
  int[] mGlobalGids;
  final ArraySet<String> mHiddenApiPackageWhitelist = new ArraySet();
  final ArraySet<String> mLinkedApps = new ArraySet();
  final ArrayMap<String, ArrayMap<String, Boolean>> mOemPermissions = new ArrayMap();
  final ArrayMap<String, PermissionEntry> mPermissions = new ArrayMap();
  final ArrayMap<String, ArraySet<String>> mPrivAppDenyPermissions = new ArrayMap();
  final ArrayMap<String, ArraySet<String>> mPrivAppPermissions = new ArrayMap();
  final ArrayMap<String, ArraySet<String>> mProductPrivAppDenyPermissions = new ArrayMap();
  final ArrayMap<String, ArraySet<String>> mProductPrivAppPermissions = new ArrayMap();
  final ArrayMap<String, String> mSharedLibraries = new ArrayMap();
  final SparseArray<ArraySet<String>> mSystemPermissions = new SparseArray();
  final ArraySet<String> mSystemUserBlacklistedApps = new ArraySet();
  final ArraySet<String> mSystemUserWhitelistedApps = new ArraySet();
  final ArraySet<String> mUnavailableFeatures = new ArraySet();
  final ArrayMap<String, ArraySet<String>> mVendorPrivAppDenyPermissions = new ArrayMap();
  final ArrayMap<String, ArraySet<String>> mVendorPrivAppPermissions = new ArrayMap();
  
  SystemConfig()
  {
    readPermissions(Environment.buildPath(Environment.getRootDirectory(), new String[] { "etc", "sysconfig" }), -1);
    readPermissions(Environment.buildPath(Environment.getRootDirectory(), new String[] { "etc", "permissions" }), -1);
    int i = 19;
    if (Build.VERSION.FIRST_SDK_INT <= 27) {
      i = 0x13 | 0xC;
    }
    readPermissions(Environment.buildPath(Environment.getVendorDirectory(), new String[] { "etc", "sysconfig" }), i);
    readPermissions(Environment.buildPath(Environment.getVendorDirectory(), new String[] { "etc", "permissions" }), i);
    readPermissions(Environment.buildPath(Environment.getOdmDirectory(), new String[] { "etc", "sysconfig" }), i);
    readPermissions(Environment.buildPath(Environment.getOdmDirectory(), new String[] { "etc", "permissions" }), i);
    readPermissions(Environment.buildPath(Environment.getOemDirectory(), new String[] { "etc", "sysconfig" }), 33);
    readPermissions(Environment.buildPath(Environment.getOemDirectory(), new String[] { "etc", "permissions" }), 33);
    readPermissions(Environment.buildPath(Environment.getProductDirectory(), new String[] { "etc", "sysconfig" }), 31);
    readPermissions(Environment.buildPath(Environment.getProductDirectory(), new String[] { "etc", "permissions" }), 31);
    if (Build.COUNTRYCODE.startsWith("RU")) {
      addFeature("com.google.android.feature.RU", 0);
    }
  }
  
  private void addFeature(String paramString, int paramInt)
  {
    FeatureInfo localFeatureInfo = (FeatureInfo)mAvailableFeatures.get(paramString);
    if (localFeatureInfo == null)
    {
      localFeatureInfo = new FeatureInfo();
      name = paramString;
      version = paramInt;
      mAvailableFeatures.put(paramString, localFeatureInfo);
    }
    else
    {
      version = Math.max(version, paramInt);
    }
  }
  
  public static SystemConfig getInstance()
  {
    try
    {
      if (sInstance == null)
      {
        localSystemConfig = new com/android/server/SystemConfig;
        localSystemConfig.<init>();
        sInstance = localSystemConfig;
      }
      SystemConfig localSystemConfig = sInstance;
      return localSystemConfig;
    }
    finally {}
  }
  
  /* Error */
  private void readPermissionsFromXml(File paramFile, int paramInt)
  {
    // Byte code:
    //   0: aconst_null
    //   1: astore_3
    //   2: new 226	java/io/FileReader
    //   5: dup
    //   6: aload_1
    //   7: invokespecial 229	java/io/FileReader:<init>	(Ljava/io/File;)V
    //   10: astore 4
    //   12: invokestatic 235	android/app/ActivityManager:isLowRamDeviceStatic	()Z
    //   15: istore 5
    //   17: aload 4
    //   19: astore 6
    //   21: aload 4
    //   23: astore 7
    //   25: invokestatic 241	android/util/Xml:newPullParser	()Lorg/xmlpull/v1/XmlPullParser;
    //   28: astore 8
    //   30: aload 4
    //   32: astore 9
    //   34: aload 4
    //   36: astore 6
    //   38: aload 4
    //   40: astore 7
    //   42: aload 8
    //   44: aload 4
    //   46: invokeinterface 247 2 0
    //   51: aload 4
    //   53: astore 9
    //   55: aload 4
    //   57: astore 6
    //   59: aload 4
    //   61: astore 7
    //   63: aload 8
    //   65: invokeinterface 251 1 0
    //   70: istore 10
    //   72: iload 10
    //   74: istore 11
    //   76: iconst_1
    //   77: istore 12
    //   79: iload 10
    //   81: iconst_2
    //   82: if_icmpeq +12 -> 94
    //   85: iload 11
    //   87: iconst_1
    //   88: if_icmpeq +6 -> 94
    //   91: goto -40 -> 51
    //   94: iload 11
    //   96: iconst_2
    //   97: if_icmpne +6260 -> 6357
    //   100: aload 4
    //   102: astore 9
    //   104: aload 4
    //   106: astore 6
    //   108: aload 4
    //   110: astore 7
    //   112: aload 8
    //   114: invokeinterface 255 1 0
    //   119: ldc -102
    //   121: invokevirtual 259	java/lang/String:equals	(Ljava/lang/Object;)Z
    //   124: istore 13
    //   126: iload 13
    //   128: ifne +245 -> 373
    //   131: aload 4
    //   133: astore 6
    //   135: aload 4
    //   137: astore 9
    //   139: aload 4
    //   141: astore 7
    //   143: aload 8
    //   145: invokeinterface 255 1 0
    //   150: ldc_w 261
    //   153: invokevirtual 259	java/lang/String:equals	(Ljava/lang/Object;)Z
    //   156: ifeq +6 -> 162
    //   159: goto +214 -> 373
    //   162: aload 4
    //   164: astore 6
    //   166: aload 4
    //   168: astore 9
    //   170: aload 4
    //   172: astore 7
    //   174: new 222	org/xmlpull/v1/XmlPullParserException
    //   177: astore 14
    //   179: aload 4
    //   181: astore 6
    //   183: aload 4
    //   185: astore 9
    //   187: aload 4
    //   189: astore 7
    //   191: new 263	java/lang/StringBuilder
    //   194: astore_3
    //   195: aload 4
    //   197: astore 6
    //   199: aload 4
    //   201: astore 9
    //   203: aload 4
    //   205: astore 7
    //   207: aload_3
    //   208: invokespecial 264	java/lang/StringBuilder:<init>	()V
    //   211: aload 4
    //   213: astore 6
    //   215: aload 4
    //   217: astore 9
    //   219: aload 4
    //   221: astore 7
    //   223: aload_3
    //   224: ldc_w 266
    //   227: invokevirtual 270	java/lang/StringBuilder:append	(Ljava/lang/String;)Ljava/lang/StringBuilder;
    //   230: pop
    //   231: aload 4
    //   233: astore 6
    //   235: aload 4
    //   237: astore 9
    //   239: aload 4
    //   241: astore 7
    //   243: aload_3
    //   244: aload_1
    //   245: invokevirtual 273	java/lang/StringBuilder:append	(Ljava/lang/Object;)Ljava/lang/StringBuilder;
    //   248: pop
    //   249: aload 4
    //   251: astore 6
    //   253: aload 4
    //   255: astore 9
    //   257: aload 4
    //   259: astore 7
    //   261: aload_3
    //   262: ldc_w 275
    //   265: invokevirtual 270	java/lang/StringBuilder:append	(Ljava/lang/String;)Ljava/lang/StringBuilder;
    //   268: pop
    //   269: aload 4
    //   271: astore 6
    //   273: aload 4
    //   275: astore 9
    //   277: aload 4
    //   279: astore 7
    //   281: aload_3
    //   282: aload 8
    //   284: invokeinterface 255 1 0
    //   289: invokevirtual 270	java/lang/StringBuilder:append	(Ljava/lang/String;)Ljava/lang/StringBuilder;
    //   292: pop
    //   293: aload 4
    //   295: astore 6
    //   297: aload 4
    //   299: astore 9
    //   301: aload 4
    //   303: astore 7
    //   305: aload_3
    //   306: ldc_w 277
    //   309: invokevirtual 270	java/lang/StringBuilder:append	(Ljava/lang/String;)Ljava/lang/StringBuilder;
    //   312: pop
    //   313: aload 4
    //   315: astore 6
    //   317: aload 4
    //   319: astore 9
    //   321: aload 4
    //   323: astore 7
    //   325: aload 14
    //   327: aload_3
    //   328: invokevirtual 280	java/lang/StringBuilder:toString	()Ljava/lang/String;
    //   331: invokespecial 283	org/xmlpull/v1/XmlPullParserException:<init>	(Ljava/lang/String;)V
    //   334: aload 4
    //   336: astore 6
    //   338: aload 4
    //   340: astore 9
    //   342: aload 4
    //   344: astore 7
    //   346: aload 14
    //   348: athrow
    //   349: astore_1
    //   350: aload 6
    //   352: astore 4
    //   354: goto +6249 -> 6603
    //   357: astore_1
    //   358: aload 9
    //   360: astore 6
    //   362: goto +6085 -> 6447
    //   365: astore 4
    //   367: aload 7
    //   369: astore_1
    //   370: goto +6112 -> 6482
    //   373: iload_2
    //   374: iconst_m1
    //   375: if_icmpne +9 -> 384
    //   378: iconst_1
    //   379: istore 15
    //   381: goto +6 -> 387
    //   384: iconst_0
    //   385: istore 15
    //   387: iload_2
    //   388: iconst_2
    //   389: iand
    //   390: ifeq +9 -> 399
    //   393: iconst_1
    //   394: istore 16
    //   396: goto +6 -> 402
    //   399: iconst_0
    //   400: istore 16
    //   402: iload_2
    //   403: iconst_1
    //   404: iand
    //   405: ifeq +9 -> 414
    //   408: iconst_1
    //   409: istore 17
    //   411: goto +6 -> 417
    //   414: iconst_0
    //   415: istore 17
    //   417: iload_2
    //   418: iconst_4
    //   419: iand
    //   420: ifeq +9 -> 429
    //   423: iconst_1
    //   424: istore 10
    //   426: goto +6 -> 432
    //   429: iconst_0
    //   430: istore 10
    //   432: iload_2
    //   433: bipush 8
    //   435: iand
    //   436: ifeq +9 -> 445
    //   439: iconst_1
    //   440: istore 18
    //   442: goto +6 -> 448
    //   445: iconst_0
    //   446: istore 18
    //   448: iload_2
    //   449: bipush 16
    //   451: iand
    //   452: ifeq +9 -> 461
    //   455: iconst_1
    //   456: istore 19
    //   458: goto +6 -> 464
    //   461: iconst_0
    //   462: istore 19
    //   464: iload_2
    //   465: bipush 32
    //   467: iand
    //   468: ifeq +9 -> 477
    //   471: iconst_1
    //   472: istore 20
    //   474: goto +6 -> 480
    //   477: iconst_0
    //   478: istore 20
    //   480: iload_2
    //   481: bipush 64
    //   483: iand
    //   484: ifeq +8 -> 492
    //   487: iconst_1
    //   488: istore_2
    //   489: goto +5 -> 494
    //   492: iconst_0
    //   493: istore_2
    //   494: aload 4
    //   496: astore 9
    //   498: aload 4
    //   500: astore 6
    //   502: aload 4
    //   504: astore 7
    //   506: aload 8
    //   508: invokestatic 289	com/android/internal/util/XmlUtils:nextElement	(Lorg/xmlpull/v1/XmlPullParser;)V
    //   511: aload 4
    //   513: astore 9
    //   515: aload 4
    //   517: astore 6
    //   519: aload 4
    //   521: astore 7
    //   523: aload 8
    //   525: invokeinterface 292 1 0
    //   530: istore 21
    //   532: iload 21
    //   534: iload 12
    //   536: if_icmpne +11 -> 547
    //   539: aload 4
    //   541: invokestatic 298	libcore/io/IoUtils:closeQuietly	(Ljava/lang/AutoCloseable;)V
    //   544: goto +5953 -> 6497
    //   547: aload 4
    //   549: astore 9
    //   551: aload 4
    //   553: astore 6
    //   555: aload 4
    //   557: astore 7
    //   559: aload 8
    //   561: invokeinterface 255 1 0
    //   566: astore 14
    //   568: aload 4
    //   570: astore 9
    //   572: aload 4
    //   574: astore 6
    //   576: aload 4
    //   578: astore 7
    //   580: ldc_w 300
    //   583: aload 14
    //   585: invokevirtual 259	java/lang/String:equals	(Ljava/lang/Object;)Z
    //   588: istore 13
    //   590: iload 13
    //   592: ifeq +238 -> 830
    //   595: iload 15
    //   597: ifeq +233 -> 830
    //   600: aload 4
    //   602: astore 6
    //   604: aload 4
    //   606: astore 9
    //   608: aload 4
    //   610: astore 7
    //   612: aload 8
    //   614: aload_3
    //   615: ldc_w 302
    //   618: invokeinterface 306 3 0
    //   623: astore_3
    //   624: aload_3
    //   625: ifnull +49 -> 674
    //   628: aload 4
    //   630: astore 6
    //   632: aload 4
    //   634: astore 9
    //   636: aload 4
    //   638: astore 7
    //   640: aload_3
    //   641: invokestatic 312	android/os/Process:getGidForName	(Ljava/lang/String;)I
    //   644: istore 12
    //   646: aload 4
    //   648: astore 6
    //   650: aload 4
    //   652: astore 9
    //   654: aload 4
    //   656: astore 7
    //   658: aload_0
    //   659: aload_0
    //   660: getfield 314	com/android/server/SystemConfig:mGlobalGids	[I
    //   663: iload 12
    //   665: invokestatic 320	com/android/internal/util/ArrayUtils:appendInt	([II)[I
    //   668: putfield 314	com/android/server/SystemConfig:mGlobalGids	[I
    //   671: goto +139 -> 810
    //   674: aload 4
    //   676: astore 6
    //   678: aload 4
    //   680: astore 9
    //   682: aload 4
    //   684: astore 7
    //   686: new 263	java/lang/StringBuilder
    //   689: astore_3
    //   690: aload 4
    //   692: astore 6
    //   694: aload 4
    //   696: astore 9
    //   698: aload 4
    //   700: astore 7
    //   702: aload_3
    //   703: invokespecial 264	java/lang/StringBuilder:<init>	()V
    //   706: aload 4
    //   708: astore 6
    //   710: aload 4
    //   712: astore 9
    //   714: aload 4
    //   716: astore 7
    //   718: aload_3
    //   719: ldc_w 322
    //   722: invokevirtual 270	java/lang/StringBuilder:append	(Ljava/lang/String;)Ljava/lang/StringBuilder;
    //   725: pop
    //   726: aload 4
    //   728: astore 6
    //   730: aload 4
    //   732: astore 9
    //   734: aload 4
    //   736: astore 7
    //   738: aload_3
    //   739: aload_1
    //   740: invokevirtual 273	java/lang/StringBuilder:append	(Ljava/lang/Object;)Ljava/lang/StringBuilder;
    //   743: pop
    //   744: aload 4
    //   746: astore 6
    //   748: aload 4
    //   750: astore 9
    //   752: aload 4
    //   754: astore 7
    //   756: aload_3
    //   757: ldc_w 324
    //   760: invokevirtual 270	java/lang/StringBuilder:append	(Ljava/lang/String;)Ljava/lang/StringBuilder;
    //   763: pop
    //   764: aload 4
    //   766: astore 6
    //   768: aload 4
    //   770: astore 9
    //   772: aload 4
    //   774: astore 7
    //   776: aload_3
    //   777: aload 8
    //   779: invokeinterface 327 1 0
    //   784: invokevirtual 270	java/lang/StringBuilder:append	(Ljava/lang/String;)Ljava/lang/StringBuilder;
    //   787: pop
    //   788: aload 4
    //   790: astore 6
    //   792: aload 4
    //   794: astore 9
    //   796: aload 4
    //   798: astore 7
    //   800: ldc 28
    //   802: aload_3
    //   803: invokevirtual 280	java/lang/StringBuilder:toString	()Ljava/lang/String;
    //   806: invokestatic 333	android/util/Slog:w	(Ljava/lang/String;Ljava/lang/String;)I
    //   809: pop
    //   810: aload 4
    //   812: astore 6
    //   814: aload 4
    //   816: astore 9
    //   818: aload 4
    //   820: astore 7
    //   822: aload 8
    //   824: invokestatic 336	com/android/internal/util/XmlUtils:skipCurrentTag	(Lorg/xmlpull/v1/XmlPullParser;)V
    //   827: goto +5522 -> 6349
    //   830: aload 4
    //   832: astore 9
    //   834: aload 4
    //   836: astore 6
    //   838: aload 4
    //   840: astore 7
    //   842: ldc_w 338
    //   845: aload 14
    //   847: invokevirtual 259	java/lang/String:equals	(Ljava/lang/Object;)Z
    //   850: istore 13
    //   852: iload 13
    //   854: ifeq +217 -> 1071
    //   857: iload 10
    //   859: ifeq +212 -> 1071
    //   862: aload 4
    //   864: astore 6
    //   866: aload 4
    //   868: astore 9
    //   870: aload 4
    //   872: astore 7
    //   874: aload 8
    //   876: aconst_null
    //   877: ldc_w 339
    //   880: invokeinterface 306 3 0
    //   885: astore_3
    //   886: aload_3
    //   887: ifnonnull +159 -> 1046
    //   890: aload 4
    //   892: astore 6
    //   894: aload 4
    //   896: astore 9
    //   898: aload 4
    //   900: astore 7
    //   902: new 263	java/lang/StringBuilder
    //   905: astore_3
    //   906: aload 4
    //   908: astore 6
    //   910: aload 4
    //   912: astore 9
    //   914: aload 4
    //   916: astore 7
    //   918: aload_3
    //   919: invokespecial 264	java/lang/StringBuilder:<init>	()V
    //   922: aload 4
    //   924: astore 6
    //   926: aload 4
    //   928: astore 9
    //   930: aload 4
    //   932: astore 7
    //   934: aload_3
    //   935: ldc_w 341
    //   938: invokevirtual 270	java/lang/StringBuilder:append	(Ljava/lang/String;)Ljava/lang/StringBuilder;
    //   941: pop
    //   942: aload 4
    //   944: astore 6
    //   946: aload 4
    //   948: astore 9
    //   950: aload 4
    //   952: astore 7
    //   954: aload_3
    //   955: aload_1
    //   956: invokevirtual 273	java/lang/StringBuilder:append	(Ljava/lang/Object;)Ljava/lang/StringBuilder;
    //   959: pop
    //   960: aload 4
    //   962: astore 6
    //   964: aload 4
    //   966: astore 9
    //   968: aload 4
    //   970: astore 7
    //   972: aload_3
    //   973: ldc_w 324
    //   976: invokevirtual 270	java/lang/StringBuilder:append	(Ljava/lang/String;)Ljava/lang/StringBuilder;
    //   979: pop
    //   980: aload 4
    //   982: astore 6
    //   984: aload 4
    //   986: astore 9
    //   988: aload 4
    //   990: astore 7
    //   992: aload_3
    //   993: aload 8
    //   995: invokeinterface 327 1 0
    //   1000: invokevirtual 270	java/lang/StringBuilder:append	(Ljava/lang/String;)Ljava/lang/StringBuilder;
    //   1003: pop
    //   1004: aload 4
    //   1006: astore 6
    //   1008: aload 4
    //   1010: astore 9
    //   1012: aload 4
    //   1014: astore 7
    //   1016: ldc 28
    //   1018: aload_3
    //   1019: invokevirtual 280	java/lang/StringBuilder:toString	()Ljava/lang/String;
    //   1022: invokestatic 333	android/util/Slog:w	(Ljava/lang/String;Ljava/lang/String;)I
    //   1025: pop
    //   1026: aload 4
    //   1028: astore 6
    //   1030: aload 4
    //   1032: astore 9
    //   1034: aload 4
    //   1036: astore 7
    //   1038: aload 8
    //   1040: invokestatic 336	com/android/internal/util/XmlUtils:skipCurrentTag	(Lorg/xmlpull/v1/XmlPullParser;)V
    //   1043: goto -216 -> 827
    //   1046: aload 4
    //   1048: astore 6
    //   1050: aload 4
    //   1052: astore 9
    //   1054: aload 4
    //   1056: astore 7
    //   1058: aload_0
    //   1059: aload 8
    //   1061: aload_3
    //   1062: invokevirtual 344	java/lang/String:intern	()Ljava/lang/String;
    //   1065: invokevirtual 348	com/android/server/SystemConfig:readPermission	(Lorg/xmlpull/v1/XmlPullParser;Ljava/lang/String;)V
    //   1068: goto +5144 -> 6212
    //   1071: aload 4
    //   1073: astore 9
    //   1075: aload 4
    //   1077: astore 6
    //   1079: aload 4
    //   1081: astore 7
    //   1083: ldc_w 350
    //   1086: aload 14
    //   1088: invokevirtual 259	java/lang/String:equals	(Ljava/lang/Object;)Z
    //   1091: ifeq +720 -> 1811
    //   1094: iload 10
    //   1096: ifeq +715 -> 1811
    //   1099: aload 4
    //   1101: astore 9
    //   1103: aload 4
    //   1105: astore 6
    //   1107: aload 4
    //   1109: astore 7
    //   1111: aload 8
    //   1113: aconst_null
    //   1114: ldc_w 339
    //   1117: invokeinterface 306 3 0
    //   1122: astore 22
    //   1124: aload 22
    //   1126: ifnonnull +159 -> 1285
    //   1129: aload 4
    //   1131: astore 6
    //   1133: aload 4
    //   1135: astore 9
    //   1137: aload 4
    //   1139: astore 7
    //   1141: new 263	java/lang/StringBuilder
    //   1144: astore_3
    //   1145: aload 4
    //   1147: astore 6
    //   1149: aload 4
    //   1151: astore 9
    //   1153: aload 4
    //   1155: astore 7
    //   1157: aload_3
    //   1158: invokespecial 264	java/lang/StringBuilder:<init>	()V
    //   1161: aload 4
    //   1163: astore 6
    //   1165: aload 4
    //   1167: astore 9
    //   1169: aload 4
    //   1171: astore 7
    //   1173: aload_3
    //   1174: ldc_w 352
    //   1177: invokevirtual 270	java/lang/StringBuilder:append	(Ljava/lang/String;)Ljava/lang/StringBuilder;
    //   1180: pop
    //   1181: aload 4
    //   1183: astore 6
    //   1185: aload 4
    //   1187: astore 9
    //   1189: aload 4
    //   1191: astore 7
    //   1193: aload_3
    //   1194: aload_1
    //   1195: invokevirtual 273	java/lang/StringBuilder:append	(Ljava/lang/Object;)Ljava/lang/StringBuilder;
    //   1198: pop
    //   1199: aload 4
    //   1201: astore 6
    //   1203: aload 4
    //   1205: astore 9
    //   1207: aload 4
    //   1209: astore 7
    //   1211: aload_3
    //   1212: ldc_w 324
    //   1215: invokevirtual 270	java/lang/StringBuilder:append	(Ljava/lang/String;)Ljava/lang/StringBuilder;
    //   1218: pop
    //   1219: aload 4
    //   1221: astore 6
    //   1223: aload 4
    //   1225: astore 9
    //   1227: aload 4
    //   1229: astore 7
    //   1231: aload_3
    //   1232: aload 8
    //   1234: invokeinterface 327 1 0
    //   1239: invokevirtual 270	java/lang/StringBuilder:append	(Ljava/lang/String;)Ljava/lang/StringBuilder;
    //   1242: pop
    //   1243: aload 4
    //   1245: astore 6
    //   1247: aload 4
    //   1249: astore 9
    //   1251: aload 4
    //   1253: astore 7
    //   1255: ldc 28
    //   1257: aload_3
    //   1258: invokevirtual 280	java/lang/StringBuilder:toString	()Ljava/lang/String;
    //   1261: invokestatic 333	android/util/Slog:w	(Ljava/lang/String;Ljava/lang/String;)I
    //   1264: pop
    //   1265: aload 4
    //   1267: astore 6
    //   1269: aload 4
    //   1271: astore 9
    //   1273: aload 4
    //   1275: astore 7
    //   1277: aload 8
    //   1279: invokestatic 336	com/android/internal/util/XmlUtils:skipCurrentTag	(Lorg/xmlpull/v1/XmlPullParser;)V
    //   1282: goto -455 -> 827
    //   1285: aload 4
    //   1287: astore 9
    //   1289: aload 4
    //   1291: astore 6
    //   1293: aload 4
    //   1295: astore 7
    //   1297: aload 8
    //   1299: aconst_null
    //   1300: ldc_w 354
    //   1303: invokeinterface 306 3 0
    //   1308: astore 14
    //   1310: aload 14
    //   1312: ifnonnull +159 -> 1471
    //   1315: aload 4
    //   1317: astore 6
    //   1319: aload 4
    //   1321: astore 9
    //   1323: aload 4
    //   1325: astore 7
    //   1327: new 263	java/lang/StringBuilder
    //   1330: astore_3
    //   1331: aload 4
    //   1333: astore 6
    //   1335: aload 4
    //   1337: astore 9
    //   1339: aload 4
    //   1341: astore 7
    //   1343: aload_3
    //   1344: invokespecial 264	java/lang/StringBuilder:<init>	()V
    //   1347: aload 4
    //   1349: astore 6
    //   1351: aload 4
    //   1353: astore 9
    //   1355: aload 4
    //   1357: astore 7
    //   1359: aload_3
    //   1360: ldc_w 356
    //   1363: invokevirtual 270	java/lang/StringBuilder:append	(Ljava/lang/String;)Ljava/lang/StringBuilder;
    //   1366: pop
    //   1367: aload 4
    //   1369: astore 6
    //   1371: aload 4
    //   1373: astore 9
    //   1375: aload 4
    //   1377: astore 7
    //   1379: aload_3
    //   1380: aload_1
    //   1381: invokevirtual 273	java/lang/StringBuilder:append	(Ljava/lang/Object;)Ljava/lang/StringBuilder;
    //   1384: pop
    //   1385: aload 4
    //   1387: astore 6
    //   1389: aload 4
    //   1391: astore 9
    //   1393: aload 4
    //   1395: astore 7
    //   1397: aload_3
    //   1398: ldc_w 324
    //   1401: invokevirtual 270	java/lang/StringBuilder:append	(Ljava/lang/String;)Ljava/lang/StringBuilder;
    //   1404: pop
    //   1405: aload 4
    //   1407: astore 6
    //   1409: aload 4
    //   1411: astore 9
    //   1413: aload 4
    //   1415: astore 7
    //   1417: aload_3
    //   1418: aload 8
    //   1420: invokeinterface 327 1 0
    //   1425: invokevirtual 270	java/lang/StringBuilder:append	(Ljava/lang/String;)Ljava/lang/StringBuilder;
    //   1428: pop
    //   1429: aload 4
    //   1431: astore 6
    //   1433: aload 4
    //   1435: astore 9
    //   1437: aload 4
    //   1439: astore 7
    //   1441: ldc 28
    //   1443: aload_3
    //   1444: invokevirtual 280	java/lang/StringBuilder:toString	()Ljava/lang/String;
    //   1447: invokestatic 333	android/util/Slog:w	(Ljava/lang/String;Ljava/lang/String;)I
    //   1450: pop
    //   1451: aload 4
    //   1453: astore 6
    //   1455: aload 4
    //   1457: astore 9
    //   1459: aload 4
    //   1461: astore 7
    //   1463: aload 8
    //   1465: invokestatic 336	com/android/internal/util/XmlUtils:skipCurrentTag	(Lorg/xmlpull/v1/XmlPullParser;)V
    //   1468: goto -641 -> 827
    //   1471: aload 4
    //   1473: astore 9
    //   1475: aload 4
    //   1477: astore 6
    //   1479: aload 4
    //   1481: astore 7
    //   1483: aload 14
    //   1485: invokestatic 359	android/os/Process:getUidForName	(Ljava/lang/String;)I
    //   1488: istore 12
    //   1490: iload 12
    //   1492: ifge +186 -> 1678
    //   1495: aload 4
    //   1497: astore 9
    //   1499: aload 4
    //   1501: astore 6
    //   1503: aload 4
    //   1505: astore 7
    //   1507: new 263	java/lang/StringBuilder
    //   1510: astore 22
    //   1512: aload 4
    //   1514: astore 9
    //   1516: aload 4
    //   1518: astore 6
    //   1520: aload 4
    //   1522: astore 7
    //   1524: aload 22
    //   1526: invokespecial 264	java/lang/StringBuilder:<init>	()V
    //   1529: aload 4
    //   1531: astore_3
    //   1532: aload_3
    //   1533: astore 7
    //   1535: aload_3
    //   1536: astore 6
    //   1538: aload_3
    //   1539: astore 9
    //   1541: aload 22
    //   1543: ldc_w 361
    //   1546: invokevirtual 270	java/lang/StringBuilder:append	(Ljava/lang/String;)Ljava/lang/StringBuilder;
    //   1549: pop
    //   1550: aload_3
    //   1551: astore 7
    //   1553: aload_3
    //   1554: astore 6
    //   1556: aload_3
    //   1557: astore 9
    //   1559: aload 22
    //   1561: aload 14
    //   1563: invokevirtual 270	java/lang/StringBuilder:append	(Ljava/lang/String;)Ljava/lang/StringBuilder;
    //   1566: pop
    //   1567: aload_3
    //   1568: astore 7
    //   1570: aload_3
    //   1571: astore 6
    //   1573: aload_3
    //   1574: astore 9
    //   1576: aload 22
    //   1578: ldc_w 363
    //   1581: invokevirtual 270	java/lang/StringBuilder:append	(Ljava/lang/String;)Ljava/lang/StringBuilder;
    //   1584: pop
    //   1585: aload_3
    //   1586: astore 7
    //   1588: aload_3
    //   1589: astore 6
    //   1591: aload_3
    //   1592: astore 9
    //   1594: aload 22
    //   1596: aload_1
    //   1597: invokevirtual 273	java/lang/StringBuilder:append	(Ljava/lang/Object;)Ljava/lang/StringBuilder;
    //   1600: pop
    //   1601: aload_3
    //   1602: astore 7
    //   1604: aload_3
    //   1605: astore 6
    //   1607: aload_3
    //   1608: astore 9
    //   1610: aload 22
    //   1612: ldc_w 324
    //   1615: invokevirtual 270	java/lang/StringBuilder:append	(Ljava/lang/String;)Ljava/lang/StringBuilder;
    //   1618: pop
    //   1619: aload_3
    //   1620: astore 7
    //   1622: aload_3
    //   1623: astore 6
    //   1625: aload_3
    //   1626: astore 9
    //   1628: aload 22
    //   1630: aload 8
    //   1632: invokeinterface 327 1 0
    //   1637: invokevirtual 270	java/lang/StringBuilder:append	(Ljava/lang/String;)Ljava/lang/StringBuilder;
    //   1640: pop
    //   1641: aload_3
    //   1642: astore 7
    //   1644: aload_3
    //   1645: astore 6
    //   1647: aload_3
    //   1648: astore 9
    //   1650: ldc 28
    //   1652: aload 22
    //   1654: invokevirtual 280	java/lang/StringBuilder:toString	()Ljava/lang/String;
    //   1657: invokestatic 333	android/util/Slog:w	(Ljava/lang/String;Ljava/lang/String;)I
    //   1660: pop
    //   1661: aload_3
    //   1662: astore 7
    //   1664: aload_3
    //   1665: astore 6
    //   1667: aload_3
    //   1668: astore 9
    //   1670: aload 8
    //   1672: invokestatic 336	com/android/internal/util/XmlUtils:skipCurrentTag	(Lorg/xmlpull/v1/XmlPullParser;)V
    //   1675: goto -848 -> 827
    //   1678: aload 4
    //   1680: astore_3
    //   1681: aload_3
    //   1682: astore 7
    //   1684: aload_3
    //   1685: astore 6
    //   1687: aload_3
    //   1688: astore 9
    //   1690: aload 22
    //   1692: invokevirtual 344	java/lang/String:intern	()Ljava/lang/String;
    //   1695: astore 23
    //   1697: aload_3
    //   1698: astore 7
    //   1700: aload_3
    //   1701: astore 6
    //   1703: aload_3
    //   1704: astore 9
    //   1706: aload_0
    //   1707: getfield 78	com/android/server/SystemConfig:mSystemPermissions	Landroid/util/SparseArray;
    //   1710: iload 12
    //   1712: invokevirtual 366	android/util/SparseArray:get	(I)Ljava/lang/Object;
    //   1715: checkcast 87	android/util/ArraySet
    //   1718: astore 22
    //   1720: aload 22
    //   1722: astore 14
    //   1724: aload 22
    //   1726: ifnonnull +51 -> 1777
    //   1729: aload_3
    //   1730: astore 7
    //   1732: aload_3
    //   1733: astore 6
    //   1735: aload_3
    //   1736: astore 9
    //   1738: new 87	android/util/ArraySet
    //   1741: astore 14
    //   1743: aload_3
    //   1744: astore 7
    //   1746: aload_3
    //   1747: astore 6
    //   1749: aload_3
    //   1750: astore 9
    //   1752: aload 14
    //   1754: invokespecial 88	android/util/ArraySet:<init>	()V
    //   1757: aload_3
    //   1758: astore 7
    //   1760: aload_3
    //   1761: astore 6
    //   1763: aload_3
    //   1764: astore 9
    //   1766: aload_0
    //   1767: getfield 78	com/android/server/SystemConfig:mSystemPermissions	Landroid/util/SparseArray;
    //   1770: iload 12
    //   1772: aload 14
    //   1774: invokevirtual 369	android/util/SparseArray:put	(ILjava/lang/Object;)V
    //   1777: aload_3
    //   1778: astore 7
    //   1780: aload_3
    //   1781: astore 6
    //   1783: aload_3
    //   1784: astore 9
    //   1786: aload 14
    //   1788: aload 23
    //   1790: invokevirtual 372	android/util/ArraySet:add	(Ljava/lang/Object;)Z
    //   1793: pop
    //   1794: aload_3
    //   1795: astore 7
    //   1797: aload_3
    //   1798: astore 6
    //   1800: aload_3
    //   1801: astore 9
    //   1803: aload 8
    //   1805: invokestatic 336	com/android/internal/util/XmlUtils:skipCurrentTag	(Lorg/xmlpull/v1/XmlPullParser;)V
    //   1808: goto -740 -> 1068
    //   1811: aload 4
    //   1813: astore_3
    //   1814: aload_3
    //   1815: astore 7
    //   1817: aload_3
    //   1818: astore 6
    //   1820: aload_3
    //   1821: astore 9
    //   1823: ldc_w 374
    //   1826: aload 14
    //   1828: invokevirtual 259	java/lang/String:equals	(Ljava/lang/Object;)Z
    //   1831: ifeq +350 -> 2181
    //   1834: iload 16
    //   1836: ifeq +345 -> 2181
    //   1839: aload_3
    //   1840: astore 7
    //   1842: aload_3
    //   1843: astore 6
    //   1845: aload_3
    //   1846: astore 9
    //   1848: aload 8
    //   1850: aconst_null
    //   1851: ldc_w 339
    //   1854: invokeinterface 306 3 0
    //   1859: astore 22
    //   1861: aload_3
    //   1862: astore 7
    //   1864: aload_3
    //   1865: astore 6
    //   1867: aload_3
    //   1868: astore 9
    //   1870: aload 8
    //   1872: aconst_null
    //   1873: ldc_w 376
    //   1876: invokeinterface 306 3 0
    //   1881: astore 14
    //   1883: aload 22
    //   1885: ifnonnull +128 -> 2013
    //   1888: aload_3
    //   1889: astore 7
    //   1891: aload_3
    //   1892: astore 6
    //   1894: aload_3
    //   1895: astore 9
    //   1897: new 263	java/lang/StringBuilder
    //   1900: astore 14
    //   1902: aload_3
    //   1903: astore 7
    //   1905: aload_3
    //   1906: astore 6
    //   1908: aload_3
    //   1909: astore 9
    //   1911: aload 14
    //   1913: invokespecial 264	java/lang/StringBuilder:<init>	()V
    //   1916: aload_3
    //   1917: astore 7
    //   1919: aload_3
    //   1920: astore 6
    //   1922: aload_3
    //   1923: astore 9
    //   1925: aload 14
    //   1927: ldc_w 378
    //   1930: invokevirtual 270	java/lang/StringBuilder:append	(Ljava/lang/String;)Ljava/lang/StringBuilder;
    //   1933: pop
    //   1934: aload_3
    //   1935: astore 7
    //   1937: aload_3
    //   1938: astore 6
    //   1940: aload_3
    //   1941: astore 9
    //   1943: aload 14
    //   1945: aload_1
    //   1946: invokevirtual 273	java/lang/StringBuilder:append	(Ljava/lang/Object;)Ljava/lang/StringBuilder;
    //   1949: pop
    //   1950: aload_3
    //   1951: astore 7
    //   1953: aload_3
    //   1954: astore 6
    //   1956: aload_3
    //   1957: astore 9
    //   1959: aload 14
    //   1961: ldc_w 324
    //   1964: invokevirtual 270	java/lang/StringBuilder:append	(Ljava/lang/String;)Ljava/lang/StringBuilder;
    //   1967: pop
    //   1968: aload_3
    //   1969: astore 7
    //   1971: aload_3
    //   1972: astore 6
    //   1974: aload_3
    //   1975: astore 9
    //   1977: aload 14
    //   1979: aload 8
    //   1981: invokeinterface 327 1 0
    //   1986: invokevirtual 270	java/lang/StringBuilder:append	(Ljava/lang/String;)Ljava/lang/StringBuilder;
    //   1989: pop
    //   1990: aload_3
    //   1991: astore 7
    //   1993: aload_3
    //   1994: astore 6
    //   1996: aload_3
    //   1997: astore 9
    //   1999: ldc 28
    //   2001: aload 14
    //   2003: invokevirtual 280	java/lang/StringBuilder:toString	()Ljava/lang/String;
    //   2006: invokestatic 333	android/util/Slog:w	(Ljava/lang/String;Ljava/lang/String;)I
    //   2009: pop
    //   2010: goto +154 -> 2164
    //   2013: aload 14
    //   2015: ifnonnull +128 -> 2143
    //   2018: aload_3
    //   2019: astore 7
    //   2021: aload_3
    //   2022: astore 6
    //   2024: aload_3
    //   2025: astore 9
    //   2027: new 263	java/lang/StringBuilder
    //   2030: astore 14
    //   2032: aload_3
    //   2033: astore 7
    //   2035: aload_3
    //   2036: astore 6
    //   2038: aload_3
    //   2039: astore 9
    //   2041: aload 14
    //   2043: invokespecial 264	java/lang/StringBuilder:<init>	()V
    //   2046: aload_3
    //   2047: astore 7
    //   2049: aload_3
    //   2050: astore 6
    //   2052: aload_3
    //   2053: astore 9
    //   2055: aload 14
    //   2057: ldc_w 380
    //   2060: invokevirtual 270	java/lang/StringBuilder:append	(Ljava/lang/String;)Ljava/lang/StringBuilder;
    //   2063: pop
    //   2064: aload_3
    //   2065: astore 7
    //   2067: aload_3
    //   2068: astore 6
    //   2070: aload_3
    //   2071: astore 9
    //   2073: aload 14
    //   2075: aload_1
    //   2076: invokevirtual 273	java/lang/StringBuilder:append	(Ljava/lang/Object;)Ljava/lang/StringBuilder;
    //   2079: pop
    //   2080: aload_3
    //   2081: astore 7
    //   2083: aload_3
    //   2084: astore 6
    //   2086: aload_3
    //   2087: astore 9
    //   2089: aload 14
    //   2091: ldc_w 324
    //   2094: invokevirtual 270	java/lang/StringBuilder:append	(Ljava/lang/String;)Ljava/lang/StringBuilder;
    //   2097: pop
    //   2098: aload_3
    //   2099: astore 7
    //   2101: aload_3
    //   2102: astore 6
    //   2104: aload_3
    //   2105: astore 9
    //   2107: aload 14
    //   2109: aload 8
    //   2111: invokeinterface 327 1 0
    //   2116: invokevirtual 270	java/lang/StringBuilder:append	(Ljava/lang/String;)Ljava/lang/StringBuilder;
    //   2119: pop
    //   2120: aload_3
    //   2121: astore 7
    //   2123: aload_3
    //   2124: astore 6
    //   2126: aload_3
    //   2127: astore 9
    //   2129: ldc 28
    //   2131: aload 14
    //   2133: invokevirtual 280	java/lang/StringBuilder:toString	()Ljava/lang/String;
    //   2136: invokestatic 333	android/util/Slog:w	(Ljava/lang/String;Ljava/lang/String;)I
    //   2139: pop
    //   2140: goto +24 -> 2164
    //   2143: aload_3
    //   2144: astore 7
    //   2146: aload_3
    //   2147: astore 6
    //   2149: aload_3
    //   2150: astore 9
    //   2152: aload_0
    //   2153: getfield 83	com/android/server/SystemConfig:mSharedLibraries	Landroid/util/ArrayMap;
    //   2156: aload 22
    //   2158: aload 14
    //   2160: invokevirtual 206	android/util/ArrayMap:put	(Ljava/lang/Object;Ljava/lang/Object;)Ljava/lang/Object;
    //   2163: pop
    //   2164: aload_3
    //   2165: astore 7
    //   2167: aload_3
    //   2168: astore 6
    //   2170: aload_3
    //   2171: astore 9
    //   2173: aload 8
    //   2175: invokestatic 336	com/android/internal/util/XmlUtils:skipCurrentTag	(Lorg/xmlpull/v1/XmlPullParser;)V
    //   2178: goto -1351 -> 827
    //   2181: aload_3
    //   2182: astore 7
    //   2184: aload_3
    //   2185: astore 6
    //   2187: aload_3
    //   2188: astore 9
    //   2190: ldc_w 382
    //   2193: aload 14
    //   2195: invokevirtual 259	java/lang/String:equals	(Ljava/lang/Object;)Z
    //   2198: ifeq +299 -> 2497
    //   2201: iload 17
    //   2203: ifeq +294 -> 2497
    //   2206: aload_3
    //   2207: astore 7
    //   2209: aload_3
    //   2210: astore 6
    //   2212: aload_3
    //   2213: astore 9
    //   2215: aload 8
    //   2217: aconst_null
    //   2218: ldc_w 339
    //   2221: invokeinterface 306 3 0
    //   2226: astore 14
    //   2228: aload_3
    //   2229: astore 7
    //   2231: aload_3
    //   2232: astore 6
    //   2234: aload_3
    //   2235: astore 9
    //   2237: aload 8
    //   2239: ldc_w 383
    //   2242: iconst_0
    //   2243: invokestatic 387	com/android/internal/util/XmlUtils:readIntAttribute	(Lorg/xmlpull/v1/XmlPullParser;Ljava/lang/String;I)I
    //   2246: istore 21
    //   2248: iload 5
    //   2250: ifne +9 -> 2259
    //   2253: iconst_1
    //   2254: istore 12
    //   2256: goto +33 -> 2289
    //   2259: aload_3
    //   2260: astore 7
    //   2262: aload_3
    //   2263: astore 6
    //   2265: aload_3
    //   2266: astore 9
    //   2268: ldc_w 389
    //   2271: aload 8
    //   2273: aconst_null
    //   2274: ldc_w 391
    //   2277: invokeinterface 306 3 0
    //   2282: invokevirtual 259	java/lang/String:equals	(Ljava/lang/Object;)Z
    //   2285: iconst_1
    //   2286: ixor
    //   2287: istore 12
    //   2289: aload 14
    //   2291: ifnonnull +128 -> 2419
    //   2294: aload_3
    //   2295: astore 7
    //   2297: aload_3
    //   2298: astore 6
    //   2300: aload_3
    //   2301: astore 9
    //   2303: new 263	java/lang/StringBuilder
    //   2306: astore 14
    //   2308: aload_3
    //   2309: astore 7
    //   2311: aload_3
    //   2312: astore 6
    //   2314: aload_3
    //   2315: astore 9
    //   2317: aload 14
    //   2319: invokespecial 264	java/lang/StringBuilder:<init>	()V
    //   2322: aload_3
    //   2323: astore 7
    //   2325: aload_3
    //   2326: astore 6
    //   2328: aload_3
    //   2329: astore 9
    //   2331: aload 14
    //   2333: ldc_w 393
    //   2336: invokevirtual 270	java/lang/StringBuilder:append	(Ljava/lang/String;)Ljava/lang/StringBuilder;
    //   2339: pop
    //   2340: aload_3
    //   2341: astore 7
    //   2343: aload_3
    //   2344: astore 6
    //   2346: aload_3
    //   2347: astore 9
    //   2349: aload 14
    //   2351: aload_1
    //   2352: invokevirtual 273	java/lang/StringBuilder:append	(Ljava/lang/Object;)Ljava/lang/StringBuilder;
    //   2355: pop
    //   2356: aload_3
    //   2357: astore 7
    //   2359: aload_3
    //   2360: astore 6
    //   2362: aload_3
    //   2363: astore 9
    //   2365: aload 14
    //   2367: ldc_w 324
    //   2370: invokevirtual 270	java/lang/StringBuilder:append	(Ljava/lang/String;)Ljava/lang/StringBuilder;
    //   2373: pop
    //   2374: aload_3
    //   2375: astore 7
    //   2377: aload_3
    //   2378: astore 6
    //   2380: aload_3
    //   2381: astore 9
    //   2383: aload 14
    //   2385: aload 8
    //   2387: invokeinterface 327 1 0
    //   2392: invokevirtual 270	java/lang/StringBuilder:append	(Ljava/lang/String;)Ljava/lang/StringBuilder;
    //   2395: pop
    //   2396: aload_3
    //   2397: astore 7
    //   2399: aload_3
    //   2400: astore 6
    //   2402: aload_3
    //   2403: astore 9
    //   2405: ldc 28
    //   2407: aload 14
    //   2409: invokevirtual 280	java/lang/StringBuilder:toString	()Ljava/lang/String;
    //   2412: invokestatic 333	android/util/Slog:w	(Ljava/lang/String;Ljava/lang/String;)I
    //   2415: pop
    //   2416: goto +64 -> 2480
    //   2419: iload 12
    //   2421: ifeq +59 -> 2480
    //   2424: aload_3
    //   2425: astore 7
    //   2427: aload_3
    //   2428: astore 6
    //   2430: aload_3
    //   2431: astore 9
    //   2433: aload 14
    //   2435: ldc_w 395
    //   2438: invokevirtual 259	java/lang/String:equals	(Ljava/lang/Object;)Z
    //   2441: ifeq +19 -> 2460
    //   2444: aload_3
    //   2445: astore 7
    //   2447: aload_3
    //   2448: astore 6
    //   2450: aload_3
    //   2451: astore 9
    //   2453: iconst_1
    //   2454: putstatic 401	android/os/Build$FEATURES:ENABLE_TWIN_APPS	Z
    //   2457: goto +3 -> 2460
    //   2460: aload_3
    //   2461: astore 7
    //   2463: aload_3
    //   2464: astore 6
    //   2466: aload_3
    //   2467: astore 9
    //   2469: aload_0
    //   2470: aload 14
    //   2472: iload 21
    //   2474: invokespecial 188	com/android/server/SystemConfig:addFeature	(Ljava/lang/String;I)V
    //   2477: goto +3 -> 2480
    //   2480: aload_3
    //   2481: astore 7
    //   2483: aload_3
    //   2484: astore 6
    //   2486: aload_3
    //   2487: astore 9
    //   2489: aload 8
    //   2491: invokestatic 336	com/android/internal/util/XmlUtils:skipCurrentTag	(Lorg/xmlpull/v1/XmlPullParser;)V
    //   2494: goto +3855 -> 6349
    //   2497: aload_3
    //   2498: astore 7
    //   2500: aload_3
    //   2501: astore 6
    //   2503: aload_3
    //   2504: astore 9
    //   2506: ldc_w 403
    //   2509: aload 14
    //   2511: invokevirtual 259	java/lang/String:equals	(Ljava/lang/Object;)Z
    //   2514: ifeq +196 -> 2710
    //   2517: iload 17
    //   2519: ifeq +191 -> 2710
    //   2522: aload_3
    //   2523: astore 7
    //   2525: aload_3
    //   2526: astore 6
    //   2528: aload_3
    //   2529: astore 9
    //   2531: aload 8
    //   2533: aconst_null
    //   2534: ldc_w 339
    //   2537: invokeinterface 306 3 0
    //   2542: astore 14
    //   2544: aload 14
    //   2546: ifnonnull +128 -> 2674
    //   2549: aload_3
    //   2550: astore 7
    //   2552: aload_3
    //   2553: astore 6
    //   2555: aload_3
    //   2556: astore 9
    //   2558: new 263	java/lang/StringBuilder
    //   2561: astore 14
    //   2563: aload_3
    //   2564: astore 7
    //   2566: aload_3
    //   2567: astore 6
    //   2569: aload_3
    //   2570: astore 9
    //   2572: aload 14
    //   2574: invokespecial 264	java/lang/StringBuilder:<init>	()V
    //   2577: aload_3
    //   2578: astore 7
    //   2580: aload_3
    //   2581: astore 6
    //   2583: aload_3
    //   2584: astore 9
    //   2586: aload 14
    //   2588: ldc_w 405
    //   2591: invokevirtual 270	java/lang/StringBuilder:append	(Ljava/lang/String;)Ljava/lang/StringBuilder;
    //   2594: pop
    //   2595: aload_3
    //   2596: astore 7
    //   2598: aload_3
    //   2599: astore 6
    //   2601: aload_3
    //   2602: astore 9
    //   2604: aload 14
    //   2606: aload_1
    //   2607: invokevirtual 273	java/lang/StringBuilder:append	(Ljava/lang/Object;)Ljava/lang/StringBuilder;
    //   2610: pop
    //   2611: aload_3
    //   2612: astore 7
    //   2614: aload_3
    //   2615: astore 6
    //   2617: aload_3
    //   2618: astore 9
    //   2620: aload 14
    //   2622: ldc_w 324
    //   2625: invokevirtual 270	java/lang/StringBuilder:append	(Ljava/lang/String;)Ljava/lang/StringBuilder;
    //   2628: pop
    //   2629: aload_3
    //   2630: astore 7
    //   2632: aload_3
    //   2633: astore 6
    //   2635: aload_3
    //   2636: astore 9
    //   2638: aload 14
    //   2640: aload 8
    //   2642: invokeinterface 327 1 0
    //   2647: invokevirtual 270	java/lang/StringBuilder:append	(Ljava/lang/String;)Ljava/lang/StringBuilder;
    //   2650: pop
    //   2651: aload_3
    //   2652: astore 7
    //   2654: aload_3
    //   2655: astore 6
    //   2657: aload_3
    //   2658: astore 9
    //   2660: ldc 28
    //   2662: aload 14
    //   2664: invokevirtual 280	java/lang/StringBuilder:toString	()Ljava/lang/String;
    //   2667: invokestatic 333	android/util/Slog:w	(Ljava/lang/String;Ljava/lang/String;)I
    //   2670: pop
    //   2671: goto +22 -> 2693
    //   2674: aload_3
    //   2675: astore 7
    //   2677: aload_3
    //   2678: astore 6
    //   2680: aload_3
    //   2681: astore 9
    //   2683: aload_0
    //   2684: getfield 90	com/android/server/SystemConfig:mUnavailableFeatures	Landroid/util/ArraySet;
    //   2687: aload 14
    //   2689: invokevirtual 372	android/util/ArraySet:add	(Ljava/lang/Object;)Z
    //   2692: pop
    //   2693: aload_3
    //   2694: astore 7
    //   2696: aload_3
    //   2697: astore 6
    //   2699: aload_3
    //   2700: astore 9
    //   2702: aload 8
    //   2704: invokestatic 336	com/android/internal/util/XmlUtils:skipCurrentTag	(Lorg/xmlpull/v1/XmlPullParser;)V
    //   2707: goto -213 -> 2494
    //   2710: aload_3
    //   2711: astore 7
    //   2713: aload_3
    //   2714: astore 6
    //   2716: aload_3
    //   2717: astore 9
    //   2719: ldc_w 407
    //   2722: aload 14
    //   2724: invokevirtual 259	java/lang/String:equals	(Ljava/lang/Object;)Z
    //   2727: ifeq +196 -> 2923
    //   2730: iload 15
    //   2732: ifeq +191 -> 2923
    //   2735: aload_3
    //   2736: astore 7
    //   2738: aload_3
    //   2739: astore 6
    //   2741: aload_3
    //   2742: astore 9
    //   2744: aload 8
    //   2746: aconst_null
    //   2747: ldc_w 409
    //   2750: invokeinterface 306 3 0
    //   2755: astore 14
    //   2757: aload 14
    //   2759: ifnonnull +128 -> 2887
    //   2762: aload_3
    //   2763: astore 7
    //   2765: aload_3
    //   2766: astore 6
    //   2768: aload_3
    //   2769: astore 9
    //   2771: new 263	java/lang/StringBuilder
    //   2774: astore 14
    //   2776: aload_3
    //   2777: astore 7
    //   2779: aload_3
    //   2780: astore 6
    //   2782: aload_3
    //   2783: astore 9
    //   2785: aload 14
    //   2787: invokespecial 264	java/lang/StringBuilder:<init>	()V
    //   2790: aload_3
    //   2791: astore 7
    //   2793: aload_3
    //   2794: astore 6
    //   2796: aload_3
    //   2797: astore 9
    //   2799: aload 14
    //   2801: ldc_w 411
    //   2804: invokevirtual 270	java/lang/StringBuilder:append	(Ljava/lang/String;)Ljava/lang/StringBuilder;
    //   2807: pop
    //   2808: aload_3
    //   2809: astore 7
    //   2811: aload_3
    //   2812: astore 6
    //   2814: aload_3
    //   2815: astore 9
    //   2817: aload 14
    //   2819: aload_1
    //   2820: invokevirtual 273	java/lang/StringBuilder:append	(Ljava/lang/Object;)Ljava/lang/StringBuilder;
    //   2823: pop
    //   2824: aload_3
    //   2825: astore 7
    //   2827: aload_3
    //   2828: astore 6
    //   2830: aload_3
    //   2831: astore 9
    //   2833: aload 14
    //   2835: ldc_w 324
    //   2838: invokevirtual 270	java/lang/StringBuilder:append	(Ljava/lang/String;)Ljava/lang/StringBuilder;
    //   2841: pop
    //   2842: aload_3
    //   2843: astore 7
    //   2845: aload_3
    //   2846: astore 6
    //   2848: aload_3
    //   2849: astore 9
    //   2851: aload 14
    //   2853: aload 8
    //   2855: invokeinterface 327 1 0
    //   2860: invokevirtual 270	java/lang/StringBuilder:append	(Ljava/lang/String;)Ljava/lang/StringBuilder;
    //   2863: pop
    //   2864: aload_3
    //   2865: astore 7
    //   2867: aload_3
    //   2868: astore 6
    //   2870: aload_3
    //   2871: astore 9
    //   2873: ldc 28
    //   2875: aload 14
    //   2877: invokevirtual 280	java/lang/StringBuilder:toString	()Ljava/lang/String;
    //   2880: invokestatic 333	android/util/Slog:w	(Ljava/lang/String;Ljava/lang/String;)I
    //   2883: pop
    //   2884: goto +22 -> 2906
    //   2887: aload_3
    //   2888: astore 7
    //   2890: aload_3
    //   2891: astore 6
    //   2893: aload_3
    //   2894: astore 9
    //   2896: aload_0
    //   2897: getfield 94	com/android/server/SystemConfig:mAllowInPowerSaveExceptIdle	Landroid/util/ArraySet;
    //   2900: aload 14
    //   2902: invokevirtual 372	android/util/ArraySet:add	(Ljava/lang/Object;)Z
    //   2905: pop
    //   2906: aload_3
    //   2907: astore 7
    //   2909: aload_3
    //   2910: astore 6
    //   2912: aload_3
    //   2913: astore 9
    //   2915: aload 8
    //   2917: invokestatic 336	com/android/internal/util/XmlUtils:skipCurrentTag	(Lorg/xmlpull/v1/XmlPullParser;)V
    //   2920: goto -426 -> 2494
    //   2923: aload_3
    //   2924: astore 7
    //   2926: aload_3
    //   2927: astore 6
    //   2929: aload_3
    //   2930: astore 9
    //   2932: ldc_w 413
    //   2935: aload 14
    //   2937: invokevirtual 259	java/lang/String:equals	(Ljava/lang/Object;)Z
    //   2940: ifeq +196 -> 3136
    //   2943: iload 15
    //   2945: ifeq +191 -> 3136
    //   2948: aload_3
    //   2949: astore 7
    //   2951: aload_3
    //   2952: astore 6
    //   2954: aload_3
    //   2955: astore 9
    //   2957: aload 8
    //   2959: aconst_null
    //   2960: ldc_w 409
    //   2963: invokeinterface 306 3 0
    //   2968: astore 14
    //   2970: aload 14
    //   2972: ifnonnull +128 -> 3100
    //   2975: aload_3
    //   2976: astore 7
    //   2978: aload_3
    //   2979: astore 6
    //   2981: aload_3
    //   2982: astore 9
    //   2984: new 263	java/lang/StringBuilder
    //   2987: astore 14
    //   2989: aload_3
    //   2990: astore 7
    //   2992: aload_3
    //   2993: astore 6
    //   2995: aload_3
    //   2996: astore 9
    //   2998: aload 14
    //   3000: invokespecial 264	java/lang/StringBuilder:<init>	()V
    //   3003: aload_3
    //   3004: astore 7
    //   3006: aload_3
    //   3007: astore 6
    //   3009: aload_3
    //   3010: astore 9
    //   3012: aload 14
    //   3014: ldc_w 415
    //   3017: invokevirtual 270	java/lang/StringBuilder:append	(Ljava/lang/String;)Ljava/lang/StringBuilder;
    //   3020: pop
    //   3021: aload_3
    //   3022: astore 7
    //   3024: aload_3
    //   3025: astore 6
    //   3027: aload_3
    //   3028: astore 9
    //   3030: aload 14
    //   3032: aload_1
    //   3033: invokevirtual 273	java/lang/StringBuilder:append	(Ljava/lang/Object;)Ljava/lang/StringBuilder;
    //   3036: pop
    //   3037: aload_3
    //   3038: astore 7
    //   3040: aload_3
    //   3041: astore 6
    //   3043: aload_3
    //   3044: astore 9
    //   3046: aload 14
    //   3048: ldc_w 324
    //   3051: invokevirtual 270	java/lang/StringBuilder:append	(Ljava/lang/String;)Ljava/lang/StringBuilder;
    //   3054: pop
    //   3055: aload_3
    //   3056: astore 7
    //   3058: aload_3
    //   3059: astore 6
    //   3061: aload_3
    //   3062: astore 9
    //   3064: aload 14
    //   3066: aload 8
    //   3068: invokeinterface 327 1 0
    //   3073: invokevirtual 270	java/lang/StringBuilder:append	(Ljava/lang/String;)Ljava/lang/StringBuilder;
    //   3076: pop
    //   3077: aload_3
    //   3078: astore 7
    //   3080: aload_3
    //   3081: astore 6
    //   3083: aload_3
    //   3084: astore 9
    //   3086: ldc 28
    //   3088: aload 14
    //   3090: invokevirtual 280	java/lang/StringBuilder:toString	()Ljava/lang/String;
    //   3093: invokestatic 333	android/util/Slog:w	(Ljava/lang/String;Ljava/lang/String;)I
    //   3096: pop
    //   3097: goto +22 -> 3119
    //   3100: aload_3
    //   3101: astore 7
    //   3103: aload_3
    //   3104: astore 6
    //   3106: aload_3
    //   3107: astore 9
    //   3109: aload_0
    //   3110: getfield 96	com/android/server/SystemConfig:mAllowInPowerSave	Landroid/util/ArraySet;
    //   3113: aload 14
    //   3115: invokevirtual 372	android/util/ArraySet:add	(Ljava/lang/Object;)Z
    //   3118: pop
    //   3119: aload_3
    //   3120: astore 7
    //   3122: aload_3
    //   3123: astore 6
    //   3125: aload_3
    //   3126: astore 9
    //   3128: aload 8
    //   3130: invokestatic 336	com/android/internal/util/XmlUtils:skipCurrentTag	(Lorg/xmlpull/v1/XmlPullParser;)V
    //   3133: goto -639 -> 2494
    //   3136: aload_3
    //   3137: astore 7
    //   3139: aload_3
    //   3140: astore 6
    //   3142: aload_3
    //   3143: astore 9
    //   3145: ldc_w 417
    //   3148: aload 14
    //   3150: invokevirtual 259	java/lang/String:equals	(Ljava/lang/Object;)Z
    //   3153: ifeq +196 -> 3349
    //   3156: iload 15
    //   3158: ifeq +191 -> 3349
    //   3161: aload_3
    //   3162: astore 7
    //   3164: aload_3
    //   3165: astore 6
    //   3167: aload_3
    //   3168: astore 9
    //   3170: aload 8
    //   3172: aconst_null
    //   3173: ldc_w 409
    //   3176: invokeinterface 306 3 0
    //   3181: astore 14
    //   3183: aload 14
    //   3185: ifnonnull +128 -> 3313
    //   3188: aload_3
    //   3189: astore 7
    //   3191: aload_3
    //   3192: astore 6
    //   3194: aload_3
    //   3195: astore 9
    //   3197: new 263	java/lang/StringBuilder
    //   3200: astore 14
    //   3202: aload_3
    //   3203: astore 7
    //   3205: aload_3
    //   3206: astore 6
    //   3208: aload_3
    //   3209: astore 9
    //   3211: aload 14
    //   3213: invokespecial 264	java/lang/StringBuilder:<init>	()V
    //   3216: aload_3
    //   3217: astore 7
    //   3219: aload_3
    //   3220: astore 6
    //   3222: aload_3
    //   3223: astore 9
    //   3225: aload 14
    //   3227: ldc_w 419
    //   3230: invokevirtual 270	java/lang/StringBuilder:append	(Ljava/lang/String;)Ljava/lang/StringBuilder;
    //   3233: pop
    //   3234: aload_3
    //   3235: astore 7
    //   3237: aload_3
    //   3238: astore 6
    //   3240: aload_3
    //   3241: astore 9
    //   3243: aload 14
    //   3245: aload_1
    //   3246: invokevirtual 273	java/lang/StringBuilder:append	(Ljava/lang/Object;)Ljava/lang/StringBuilder;
    //   3249: pop
    //   3250: aload_3
    //   3251: astore 7
    //   3253: aload_3
    //   3254: astore 6
    //   3256: aload_3
    //   3257: astore 9
    //   3259: aload 14
    //   3261: ldc_w 324
    //   3264: invokevirtual 270	java/lang/StringBuilder:append	(Ljava/lang/String;)Ljava/lang/StringBuilder;
    //   3267: pop
    //   3268: aload_3
    //   3269: astore 7
    //   3271: aload_3
    //   3272: astore 6
    //   3274: aload_3
    //   3275: astore 9
    //   3277: aload 14
    //   3279: aload 8
    //   3281: invokeinterface 327 1 0
    //   3286: invokevirtual 270	java/lang/StringBuilder:append	(Ljava/lang/String;)Ljava/lang/StringBuilder;
    //   3289: pop
    //   3290: aload_3
    //   3291: astore 7
    //   3293: aload_3
    //   3294: astore 6
    //   3296: aload_3
    //   3297: astore 9
    //   3299: ldc 28
    //   3301: aload 14
    //   3303: invokevirtual 280	java/lang/StringBuilder:toString	()Ljava/lang/String;
    //   3306: invokestatic 333	android/util/Slog:w	(Ljava/lang/String;Ljava/lang/String;)I
    //   3309: pop
    //   3310: goto +22 -> 3332
    //   3313: aload_3
    //   3314: astore 7
    //   3316: aload_3
    //   3317: astore 6
    //   3319: aload_3
    //   3320: astore 9
    //   3322: aload_0
    //   3323: getfield 98	com/android/server/SystemConfig:mAllowInDataUsageSave	Landroid/util/ArraySet;
    //   3326: aload 14
    //   3328: invokevirtual 372	android/util/ArraySet:add	(Ljava/lang/Object;)Z
    //   3331: pop
    //   3332: aload_3
    //   3333: astore 7
    //   3335: aload_3
    //   3336: astore 6
    //   3338: aload_3
    //   3339: astore 9
    //   3341: aload 8
    //   3343: invokestatic 336	com/android/internal/util/XmlUtils:skipCurrentTag	(Lorg/xmlpull/v1/XmlPullParser;)V
    //   3346: goto -852 -> 2494
    //   3349: aload_3
    //   3350: astore 7
    //   3352: aload_3
    //   3353: astore 6
    //   3355: aload_3
    //   3356: astore 9
    //   3358: ldc_w 421
    //   3361: aload 14
    //   3363: invokevirtual 259	java/lang/String:equals	(Ljava/lang/Object;)Z
    //   3366: ifeq +196 -> 3562
    //   3369: iload 15
    //   3371: ifeq +191 -> 3562
    //   3374: aload_3
    //   3375: astore 7
    //   3377: aload_3
    //   3378: astore 6
    //   3380: aload_3
    //   3381: astore 9
    //   3383: aload 8
    //   3385: aconst_null
    //   3386: ldc_w 409
    //   3389: invokeinterface 306 3 0
    //   3394: astore 14
    //   3396: aload 14
    //   3398: ifnonnull +128 -> 3526
    //   3401: aload_3
    //   3402: astore 7
    //   3404: aload_3
    //   3405: astore 6
    //   3407: aload_3
    //   3408: astore 9
    //   3410: new 263	java/lang/StringBuilder
    //   3413: astore 14
    //   3415: aload_3
    //   3416: astore 7
    //   3418: aload_3
    //   3419: astore 6
    //   3421: aload_3
    //   3422: astore 9
    //   3424: aload 14
    //   3426: invokespecial 264	java/lang/StringBuilder:<init>	()V
    //   3429: aload_3
    //   3430: astore 7
    //   3432: aload_3
    //   3433: astore 6
    //   3435: aload_3
    //   3436: astore 9
    //   3438: aload 14
    //   3440: ldc_w 423
    //   3443: invokevirtual 270	java/lang/StringBuilder:append	(Ljava/lang/String;)Ljava/lang/StringBuilder;
    //   3446: pop
    //   3447: aload_3
    //   3448: astore 7
    //   3450: aload_3
    //   3451: astore 6
    //   3453: aload_3
    //   3454: astore 9
    //   3456: aload 14
    //   3458: aload_1
    //   3459: invokevirtual 273	java/lang/StringBuilder:append	(Ljava/lang/Object;)Ljava/lang/StringBuilder;
    //   3462: pop
    //   3463: aload_3
    //   3464: astore 7
    //   3466: aload_3
    //   3467: astore 6
    //   3469: aload_3
    //   3470: astore 9
    //   3472: aload 14
    //   3474: ldc_w 324
    //   3477: invokevirtual 270	java/lang/StringBuilder:append	(Ljava/lang/String;)Ljava/lang/StringBuilder;
    //   3480: pop
    //   3481: aload_3
    //   3482: astore 7
    //   3484: aload_3
    //   3485: astore 6
    //   3487: aload_3
    //   3488: astore 9
    //   3490: aload 14
    //   3492: aload 8
    //   3494: invokeinterface 327 1 0
    //   3499: invokevirtual 270	java/lang/StringBuilder:append	(Ljava/lang/String;)Ljava/lang/StringBuilder;
    //   3502: pop
    //   3503: aload_3
    //   3504: astore 7
    //   3506: aload_3
    //   3507: astore 6
    //   3509: aload_3
    //   3510: astore 9
    //   3512: ldc 28
    //   3514: aload 14
    //   3516: invokevirtual 280	java/lang/StringBuilder:toString	()Ljava/lang/String;
    //   3519: invokestatic 333	android/util/Slog:w	(Ljava/lang/String;Ljava/lang/String;)I
    //   3522: pop
    //   3523: goto +22 -> 3545
    //   3526: aload_3
    //   3527: astore 7
    //   3529: aload_3
    //   3530: astore 6
    //   3532: aload_3
    //   3533: astore 9
    //   3535: aload_0
    //   3536: getfield 100	com/android/server/SystemConfig:mAllowUnthrottledLocation	Landroid/util/ArraySet;
    //   3539: aload 14
    //   3541: invokevirtual 372	android/util/ArraySet:add	(Ljava/lang/Object;)Z
    //   3544: pop
    //   3545: aload_3
    //   3546: astore 7
    //   3548: aload_3
    //   3549: astore 6
    //   3551: aload_3
    //   3552: astore 9
    //   3554: aload 8
    //   3556: invokestatic 336	com/android/internal/util/XmlUtils:skipCurrentTag	(Lorg/xmlpull/v1/XmlPullParser;)V
    //   3559: goto -1065 -> 2494
    //   3562: aload_3
    //   3563: astore 7
    //   3565: aload_3
    //   3566: astore 6
    //   3568: aload_3
    //   3569: astore 9
    //   3571: ldc_w 425
    //   3574: aload 14
    //   3576: invokevirtual 259	java/lang/String:equals	(Ljava/lang/Object;)Z
    //   3579: ifeq +196 -> 3775
    //   3582: iload 15
    //   3584: ifeq +191 -> 3775
    //   3587: aload_3
    //   3588: astore 7
    //   3590: aload_3
    //   3591: astore 6
    //   3593: aload_3
    //   3594: astore 9
    //   3596: aload 8
    //   3598: aconst_null
    //   3599: ldc_w 427
    //   3602: invokeinterface 306 3 0
    //   3607: astore 14
    //   3609: aload 14
    //   3611: ifnonnull +128 -> 3739
    //   3614: aload_3
    //   3615: astore 7
    //   3617: aload_3
    //   3618: astore 6
    //   3620: aload_3
    //   3621: astore 9
    //   3623: new 263	java/lang/StringBuilder
    //   3626: astore 14
    //   3628: aload_3
    //   3629: astore 7
    //   3631: aload_3
    //   3632: astore 6
    //   3634: aload_3
    //   3635: astore 9
    //   3637: aload 14
    //   3639: invokespecial 264	java/lang/StringBuilder:<init>	()V
    //   3642: aload_3
    //   3643: astore 7
    //   3645: aload_3
    //   3646: astore 6
    //   3648: aload_3
    //   3649: astore 9
    //   3651: aload 14
    //   3653: ldc_w 429
    //   3656: invokevirtual 270	java/lang/StringBuilder:append	(Ljava/lang/String;)Ljava/lang/StringBuilder;
    //   3659: pop
    //   3660: aload_3
    //   3661: astore 7
    //   3663: aload_3
    //   3664: astore 6
    //   3666: aload_3
    //   3667: astore 9
    //   3669: aload 14
    //   3671: aload_1
    //   3672: invokevirtual 273	java/lang/StringBuilder:append	(Ljava/lang/Object;)Ljava/lang/StringBuilder;
    //   3675: pop
    //   3676: aload_3
    //   3677: astore 7
    //   3679: aload_3
    //   3680: astore 6
    //   3682: aload_3
    //   3683: astore 9
    //   3685: aload 14
    //   3687: ldc_w 324
    //   3690: invokevirtual 270	java/lang/StringBuilder:append	(Ljava/lang/String;)Ljava/lang/StringBuilder;
    //   3693: pop
    //   3694: aload_3
    //   3695: astore 7
    //   3697: aload_3
    //   3698: astore 6
    //   3700: aload_3
    //   3701: astore 9
    //   3703: aload 14
    //   3705: aload 8
    //   3707: invokeinterface 327 1 0
    //   3712: invokevirtual 270	java/lang/StringBuilder:append	(Ljava/lang/String;)Ljava/lang/StringBuilder;
    //   3715: pop
    //   3716: aload_3
    //   3717: astore 7
    //   3719: aload_3
    //   3720: astore 6
    //   3722: aload_3
    //   3723: astore 9
    //   3725: ldc 28
    //   3727: aload 14
    //   3729: invokevirtual 280	java/lang/StringBuilder:toString	()Ljava/lang/String;
    //   3732: invokestatic 333	android/util/Slog:w	(Ljava/lang/String;Ljava/lang/String;)I
    //   3735: pop
    //   3736: goto +22 -> 3758
    //   3739: aload_3
    //   3740: astore 7
    //   3742: aload_3
    //   3743: astore 6
    //   3745: aload_3
    //   3746: astore 9
    //   3748: aload_0
    //   3749: getfield 102	com/android/server/SystemConfig:mAllowImplicitBroadcasts	Landroid/util/ArraySet;
    //   3752: aload 14
    //   3754: invokevirtual 372	android/util/ArraySet:add	(Ljava/lang/Object;)Z
    //   3757: pop
    //   3758: aload_3
    //   3759: astore 7
    //   3761: aload_3
    //   3762: astore 6
    //   3764: aload_3
    //   3765: astore 9
    //   3767: aload 8
    //   3769: invokestatic 336	com/android/internal/util/XmlUtils:skipCurrentTag	(Lorg/xmlpull/v1/XmlPullParser;)V
    //   3772: goto -1278 -> 2494
    //   3775: aload_3
    //   3776: astore 7
    //   3778: aload_3
    //   3779: astore 6
    //   3781: aload_3
    //   3782: astore 9
    //   3784: ldc_w 431
    //   3787: aload 14
    //   3789: invokevirtual 259	java/lang/String:equals	(Ljava/lang/Object;)Z
    //   3792: ifeq +196 -> 3988
    //   3795: iload 18
    //   3797: ifeq +191 -> 3988
    //   3800: aload_3
    //   3801: astore 7
    //   3803: aload_3
    //   3804: astore 6
    //   3806: aload_3
    //   3807: astore 9
    //   3809: aload 8
    //   3811: aconst_null
    //   3812: ldc_w 409
    //   3815: invokeinterface 306 3 0
    //   3820: astore 14
    //   3822: aload 14
    //   3824: ifnonnull +128 -> 3952
    //   3827: aload_3
    //   3828: astore 7
    //   3830: aload_3
    //   3831: astore 6
    //   3833: aload_3
    //   3834: astore 9
    //   3836: new 263	java/lang/StringBuilder
    //   3839: astore 14
    //   3841: aload_3
    //   3842: astore 7
    //   3844: aload_3
    //   3845: astore 6
    //   3847: aload_3
    //   3848: astore 9
    //   3850: aload 14
    //   3852: invokespecial 264	java/lang/StringBuilder:<init>	()V
    //   3855: aload_3
    //   3856: astore 7
    //   3858: aload_3
    //   3859: astore 6
    //   3861: aload_3
    //   3862: astore 9
    //   3864: aload 14
    //   3866: ldc_w 433
    //   3869: invokevirtual 270	java/lang/StringBuilder:append	(Ljava/lang/String;)Ljava/lang/StringBuilder;
    //   3872: pop
    //   3873: aload_3
    //   3874: astore 7
    //   3876: aload_3
    //   3877: astore 6
    //   3879: aload_3
    //   3880: astore 9
    //   3882: aload 14
    //   3884: aload_1
    //   3885: invokevirtual 273	java/lang/StringBuilder:append	(Ljava/lang/Object;)Ljava/lang/StringBuilder;
    //   3888: pop
    //   3889: aload_3
    //   3890: astore 7
    //   3892: aload_3
    //   3893: astore 6
    //   3895: aload_3
    //   3896: astore 9
    //   3898: aload 14
    //   3900: ldc_w 324
    //   3903: invokevirtual 270	java/lang/StringBuilder:append	(Ljava/lang/String;)Ljava/lang/StringBuilder;
    //   3906: pop
    //   3907: aload_3
    //   3908: astore 7
    //   3910: aload_3
    //   3911: astore 6
    //   3913: aload_3
    //   3914: astore 9
    //   3916: aload 14
    //   3918: aload 8
    //   3920: invokeinterface 327 1 0
    //   3925: invokevirtual 270	java/lang/StringBuilder:append	(Ljava/lang/String;)Ljava/lang/StringBuilder;
    //   3928: pop
    //   3929: aload_3
    //   3930: astore 7
    //   3932: aload_3
    //   3933: astore 6
    //   3935: aload_3
    //   3936: astore 9
    //   3938: ldc 28
    //   3940: aload 14
    //   3942: invokevirtual 280	java/lang/StringBuilder:toString	()Ljava/lang/String;
    //   3945: invokestatic 333	android/util/Slog:w	(Ljava/lang/String;Ljava/lang/String;)I
    //   3948: pop
    //   3949: goto +22 -> 3971
    //   3952: aload_3
    //   3953: astore 7
    //   3955: aload_3
    //   3956: astore 6
    //   3958: aload_3
    //   3959: astore 9
    //   3961: aload_0
    //   3962: getfield 104	com/android/server/SystemConfig:mLinkedApps	Landroid/util/ArraySet;
    //   3965: aload 14
    //   3967: invokevirtual 372	android/util/ArraySet:add	(Ljava/lang/Object;)Z
    //   3970: pop
    //   3971: aload_3
    //   3972: astore 7
    //   3974: aload_3
    //   3975: astore 6
    //   3977: aload_3
    //   3978: astore 9
    //   3980: aload 8
    //   3982: invokestatic 336	com/android/internal/util/XmlUtils:skipCurrentTag	(Lorg/xmlpull/v1/XmlPullParser;)V
    //   3985: goto +2227 -> 6212
    //   3988: aload_3
    //   3989: astore 7
    //   3991: aload_3
    //   3992: astore 6
    //   3994: aload_3
    //   3995: astore 9
    //   3997: ldc_w 435
    //   4000: aload 14
    //   4002: invokevirtual 259	java/lang/String:equals	(Ljava/lang/Object;)Z
    //   4005: ifeq +196 -> 4201
    //   4008: iload 18
    //   4010: ifeq +191 -> 4201
    //   4013: aload_3
    //   4014: astore 7
    //   4016: aload_3
    //   4017: astore 6
    //   4019: aload_3
    //   4020: astore 9
    //   4022: aload 8
    //   4024: aconst_null
    //   4025: ldc_w 409
    //   4028: invokeinterface 306 3 0
    //   4033: astore 14
    //   4035: aload 14
    //   4037: ifnonnull +128 -> 4165
    //   4040: aload_3
    //   4041: astore 7
    //   4043: aload_3
    //   4044: astore 6
    //   4046: aload_3
    //   4047: astore 9
    //   4049: new 263	java/lang/StringBuilder
    //   4052: astore 14
    //   4054: aload_3
    //   4055: astore 7
    //   4057: aload_3
    //   4058: astore 6
    //   4060: aload_3
    //   4061: astore 9
    //   4063: aload 14
    //   4065: invokespecial 264	java/lang/StringBuilder:<init>	()V
    //   4068: aload_3
    //   4069: astore 7
    //   4071: aload_3
    //   4072: astore 6
    //   4074: aload_3
    //   4075: astore 9
    //   4077: aload 14
    //   4079: ldc_w 437
    //   4082: invokevirtual 270	java/lang/StringBuilder:append	(Ljava/lang/String;)Ljava/lang/StringBuilder;
    //   4085: pop
    //   4086: aload_3
    //   4087: astore 7
    //   4089: aload_3
    //   4090: astore 6
    //   4092: aload_3
    //   4093: astore 9
    //   4095: aload 14
    //   4097: aload_1
    //   4098: invokevirtual 273	java/lang/StringBuilder:append	(Ljava/lang/Object;)Ljava/lang/StringBuilder;
    //   4101: pop
    //   4102: aload_3
    //   4103: astore 7
    //   4105: aload_3
    //   4106: astore 6
    //   4108: aload_3
    //   4109: astore 9
    //   4111: aload 14
    //   4113: ldc_w 324
    //   4116: invokevirtual 270	java/lang/StringBuilder:append	(Ljava/lang/String;)Ljava/lang/StringBuilder;
    //   4119: pop
    //   4120: aload_3
    //   4121: astore 7
    //   4123: aload_3
    //   4124: astore 6
    //   4126: aload_3
    //   4127: astore 9
    //   4129: aload 14
    //   4131: aload 8
    //   4133: invokeinterface 327 1 0
    //   4138: invokevirtual 270	java/lang/StringBuilder:append	(Ljava/lang/String;)Ljava/lang/StringBuilder;
    //   4141: pop
    //   4142: aload_3
    //   4143: astore 7
    //   4145: aload_3
    //   4146: astore 6
    //   4148: aload_3
    //   4149: astore 9
    //   4151: ldc 28
    //   4153: aload 14
    //   4155: invokevirtual 280	java/lang/StringBuilder:toString	()Ljava/lang/String;
    //   4158: invokestatic 333	android/util/Slog:w	(Ljava/lang/String;Ljava/lang/String;)I
    //   4161: pop
    //   4162: goto +22 -> 4184
    //   4165: aload_3
    //   4166: astore 7
    //   4168: aload_3
    //   4169: astore 6
    //   4171: aload_3
    //   4172: astore 9
    //   4174: aload_0
    //   4175: getfield 106	com/android/server/SystemConfig:mSystemUserWhitelistedApps	Landroid/util/ArraySet;
    //   4178: aload 14
    //   4180: invokevirtual 372	android/util/ArraySet:add	(Ljava/lang/Object;)Z
    //   4183: pop
    //   4184: aload_3
    //   4185: astore 7
    //   4187: aload_3
    //   4188: astore 6
    //   4190: aload_3
    //   4191: astore 9
    //   4193: aload 8
    //   4195: invokestatic 336	com/android/internal/util/XmlUtils:skipCurrentTag	(Lorg/xmlpull/v1/XmlPullParser;)V
    //   4198: goto -213 -> 3985
    //   4201: aload_3
    //   4202: astore 7
    //   4204: aload_3
    //   4205: astore 6
    //   4207: aload_3
    //   4208: astore 9
    //   4210: ldc_w 439
    //   4213: aload 14
    //   4215: invokevirtual 259	java/lang/String:equals	(Ljava/lang/Object;)Z
    //   4218: ifeq +196 -> 4414
    //   4221: iload 18
    //   4223: ifeq +191 -> 4414
    //   4226: aload_3
    //   4227: astore 7
    //   4229: aload_3
    //   4230: astore 6
    //   4232: aload_3
    //   4233: astore 9
    //   4235: aload 8
    //   4237: aconst_null
    //   4238: ldc_w 409
    //   4241: invokeinterface 306 3 0
    //   4246: astore 14
    //   4248: aload 14
    //   4250: ifnonnull +128 -> 4378
    //   4253: aload_3
    //   4254: astore 7
    //   4256: aload_3
    //   4257: astore 6
    //   4259: aload_3
    //   4260: astore 9
    //   4262: new 263	java/lang/StringBuilder
    //   4265: astore 14
    //   4267: aload_3
    //   4268: astore 7
    //   4270: aload_3
    //   4271: astore 6
    //   4273: aload_3
    //   4274: astore 9
    //   4276: aload 14
    //   4278: invokespecial 264	java/lang/StringBuilder:<init>	()V
    //   4281: aload_3
    //   4282: astore 7
    //   4284: aload_3
    //   4285: astore 6
    //   4287: aload_3
    //   4288: astore 9
    //   4290: aload 14
    //   4292: ldc_w 441
    //   4295: invokevirtual 270	java/lang/StringBuilder:append	(Ljava/lang/String;)Ljava/lang/StringBuilder;
    //   4298: pop
    //   4299: aload_3
    //   4300: astore 7
    //   4302: aload_3
    //   4303: astore 6
    //   4305: aload_3
    //   4306: astore 9
    //   4308: aload 14
    //   4310: aload_1
    //   4311: invokevirtual 273	java/lang/StringBuilder:append	(Ljava/lang/Object;)Ljava/lang/StringBuilder;
    //   4314: pop
    //   4315: aload_3
    //   4316: astore 7
    //   4318: aload_3
    //   4319: astore 6
    //   4321: aload_3
    //   4322: astore 9
    //   4324: aload 14
    //   4326: ldc_w 324
    //   4329: invokevirtual 270	java/lang/StringBuilder:append	(Ljava/lang/String;)Ljava/lang/StringBuilder;
    //   4332: pop
    //   4333: aload_3
    //   4334: astore 7
    //   4336: aload_3
    //   4337: astore 6
    //   4339: aload_3
    //   4340: astore 9
    //   4342: aload 14
    //   4344: aload 8
    //   4346: invokeinterface 327 1 0
    //   4351: invokevirtual 270	java/lang/StringBuilder:append	(Ljava/lang/String;)Ljava/lang/StringBuilder;
    //   4354: pop
    //   4355: aload_3
    //   4356: astore 7
    //   4358: aload_3
    //   4359: astore 6
    //   4361: aload_3
    //   4362: astore 9
    //   4364: ldc 28
    //   4366: aload 14
    //   4368: invokevirtual 280	java/lang/StringBuilder:toString	()Ljava/lang/String;
    //   4371: invokestatic 333	android/util/Slog:w	(Ljava/lang/String;Ljava/lang/String;)I
    //   4374: pop
    //   4375: goto +22 -> 4397
    //   4378: aload_3
    //   4379: astore 7
    //   4381: aload_3
    //   4382: astore 6
    //   4384: aload_3
    //   4385: astore 9
    //   4387: aload_0
    //   4388: getfield 108	com/android/server/SystemConfig:mSystemUserBlacklistedApps	Landroid/util/ArraySet;
    //   4391: aload 14
    //   4393: invokevirtual 372	android/util/ArraySet:add	(Ljava/lang/Object;)Z
    //   4396: pop
    //   4397: aload_3
    //   4398: astore 7
    //   4400: aload_3
    //   4401: astore 6
    //   4403: aload_3
    //   4404: astore 9
    //   4406: aload 8
    //   4408: invokestatic 336	com/android/internal/util/XmlUtils:skipCurrentTag	(Lorg/xmlpull/v1/XmlPullParser;)V
    //   4411: goto -426 -> 3985
    //   4414: aload_3
    //   4415: astore 7
    //   4417: aload_3
    //   4418: astore 6
    //   4420: aload_3
    //   4421: astore 9
    //   4423: ldc_w 443
    //   4426: aload 14
    //   4428: invokevirtual 259	java/lang/String:equals	(Ljava/lang/Object;)Z
    //   4431: ifeq +393 -> 4824
    //   4434: iload 18
    //   4436: ifeq +388 -> 4824
    //   4439: aload_3
    //   4440: astore 7
    //   4442: aload_3
    //   4443: astore 6
    //   4445: aload_3
    //   4446: astore 9
    //   4448: aload 8
    //   4450: aconst_null
    //   4451: ldc_w 409
    //   4454: invokeinterface 306 3 0
    //   4459: astore 14
    //   4461: aload_3
    //   4462: astore 7
    //   4464: aload_3
    //   4465: astore 6
    //   4467: aload_3
    //   4468: astore 9
    //   4470: aload 8
    //   4472: aconst_null
    //   4473: ldc_w 445
    //   4476: invokeinterface 306 3 0
    //   4481: astore 23
    //   4483: aload 14
    //   4485: ifnonnull +128 -> 4613
    //   4488: aload_3
    //   4489: astore 7
    //   4491: aload_3
    //   4492: astore 6
    //   4494: aload_3
    //   4495: astore 9
    //   4497: new 263	java/lang/StringBuilder
    //   4500: astore 14
    //   4502: aload_3
    //   4503: astore 7
    //   4505: aload_3
    //   4506: astore 6
    //   4508: aload_3
    //   4509: astore 9
    //   4511: aload 14
    //   4513: invokespecial 264	java/lang/StringBuilder:<init>	()V
    //   4516: aload_3
    //   4517: astore 7
    //   4519: aload_3
    //   4520: astore 6
    //   4522: aload_3
    //   4523: astore 9
    //   4525: aload 14
    //   4527: ldc_w 447
    //   4530: invokevirtual 270	java/lang/StringBuilder:append	(Ljava/lang/String;)Ljava/lang/StringBuilder;
    //   4533: pop
    //   4534: aload_3
    //   4535: astore 7
    //   4537: aload_3
    //   4538: astore 6
    //   4540: aload_3
    //   4541: astore 9
    //   4543: aload 14
    //   4545: aload_1
    //   4546: invokevirtual 273	java/lang/StringBuilder:append	(Ljava/lang/Object;)Ljava/lang/StringBuilder;
    //   4549: pop
    //   4550: aload_3
    //   4551: astore 7
    //   4553: aload_3
    //   4554: astore 6
    //   4556: aload_3
    //   4557: astore 9
    //   4559: aload 14
    //   4561: ldc_w 324
    //   4564: invokevirtual 270	java/lang/StringBuilder:append	(Ljava/lang/String;)Ljava/lang/StringBuilder;
    //   4567: pop
    //   4568: aload_3
    //   4569: astore 7
    //   4571: aload_3
    //   4572: astore 6
    //   4574: aload_3
    //   4575: astore 9
    //   4577: aload 14
    //   4579: aload 8
    //   4581: invokeinterface 327 1 0
    //   4586: invokevirtual 270	java/lang/StringBuilder:append	(Ljava/lang/String;)Ljava/lang/StringBuilder;
    //   4589: pop
    //   4590: aload_3
    //   4591: astore 7
    //   4593: aload_3
    //   4594: astore 6
    //   4596: aload_3
    //   4597: astore 9
    //   4599: ldc 28
    //   4601: aload 14
    //   4603: invokevirtual 280	java/lang/StringBuilder:toString	()Ljava/lang/String;
    //   4606: invokestatic 333	android/util/Slog:w	(Ljava/lang/String;Ljava/lang/String;)I
    //   4609: pop
    //   4610: goto +197 -> 4807
    //   4613: aload 23
    //   4615: ifnonnull +128 -> 4743
    //   4618: aload_3
    //   4619: astore 7
    //   4621: aload_3
    //   4622: astore 6
    //   4624: aload_3
    //   4625: astore 9
    //   4627: new 263	java/lang/StringBuilder
    //   4630: astore 14
    //   4632: aload_3
    //   4633: astore 7
    //   4635: aload_3
    //   4636: astore 6
    //   4638: aload_3
    //   4639: astore 9
    //   4641: aload 14
    //   4643: invokespecial 264	java/lang/StringBuilder:<init>	()V
    //   4646: aload_3
    //   4647: astore 7
    //   4649: aload_3
    //   4650: astore 6
    //   4652: aload_3
    //   4653: astore 9
    //   4655: aload 14
    //   4657: ldc_w 449
    //   4660: invokevirtual 270	java/lang/StringBuilder:append	(Ljava/lang/String;)Ljava/lang/StringBuilder;
    //   4663: pop
    //   4664: aload_3
    //   4665: astore 7
    //   4667: aload_3
    //   4668: astore 6
    //   4670: aload_3
    //   4671: astore 9
    //   4673: aload 14
    //   4675: aload_1
    //   4676: invokevirtual 273	java/lang/StringBuilder:append	(Ljava/lang/Object;)Ljava/lang/StringBuilder;
    //   4679: pop
    //   4680: aload_3
    //   4681: astore 7
    //   4683: aload_3
    //   4684: astore 6
    //   4686: aload_3
    //   4687: astore 9
    //   4689: aload 14
    //   4691: ldc_w 324
    //   4694: invokevirtual 270	java/lang/StringBuilder:append	(Ljava/lang/String;)Ljava/lang/StringBuilder;
    //   4697: pop
    //   4698: aload_3
    //   4699: astore 7
    //   4701: aload_3
    //   4702: astore 6
    //   4704: aload_3
    //   4705: astore 9
    //   4707: aload 14
    //   4709: aload 8
    //   4711: invokeinterface 327 1 0
    //   4716: invokevirtual 270	java/lang/StringBuilder:append	(Ljava/lang/String;)Ljava/lang/StringBuilder;
    //   4719: pop
    //   4720: aload_3
    //   4721: astore 7
    //   4723: aload_3
    //   4724: astore 6
    //   4726: aload_3
    //   4727: astore 9
    //   4729: ldc 28
    //   4731: aload 14
    //   4733: invokevirtual 280	java/lang/StringBuilder:toString	()Ljava/lang/String;
    //   4736: invokestatic 333	android/util/Slog:w	(Ljava/lang/String;Ljava/lang/String;)I
    //   4739: pop
    //   4740: goto +67 -> 4807
    //   4743: aload_3
    //   4744: astore 7
    //   4746: aload_3
    //   4747: astore 6
    //   4749: aload_3
    //   4750: astore 9
    //   4752: aload_0
    //   4753: getfield 110	com/android/server/SystemConfig:mDefaultVrComponents	Landroid/util/ArraySet;
    //   4756: astore 22
    //   4758: aload_3
    //   4759: astore 7
    //   4761: aload_3
    //   4762: astore 6
    //   4764: aload_3
    //   4765: astore 9
    //   4767: new 451	android/content/ComponentName
    //   4770: astore 24
    //   4772: aload_3
    //   4773: astore 7
    //   4775: aload_3
    //   4776: astore 6
    //   4778: aload_3
    //   4779: astore 9
    //   4781: aload 24
    //   4783: aload 14
    //   4785: aload 23
    //   4787: invokespecial 454	android/content/ComponentName:<init>	(Ljava/lang/String;Ljava/lang/String;)V
    //   4790: aload_3
    //   4791: astore 7
    //   4793: aload_3
    //   4794: astore 6
    //   4796: aload_3
    //   4797: astore 9
    //   4799: aload 22
    //   4801: aload 24
    //   4803: invokevirtual 372	android/util/ArraySet:add	(Ljava/lang/Object;)Z
    //   4806: pop
    //   4807: aload_3
    //   4808: astore 7
    //   4810: aload_3
    //   4811: astore 6
    //   4813: aload_3
    //   4814: astore 9
    //   4816: aload 8
    //   4818: invokestatic 336	com/android/internal/util/XmlUtils:skipCurrentTag	(Lorg/xmlpull/v1/XmlPullParser;)V
    //   4821: goto -836 -> 3985
    //   4824: aload_3
    //   4825: astore 7
    //   4827: aload_3
    //   4828: astore 6
    //   4830: aload_3
    //   4831: astore 9
    //   4833: ldc_w 456
    //   4836: aload 14
    //   4838: invokevirtual 259	java/lang/String:equals	(Ljava/lang/Object;)Z
    //   4841: ifeq +377 -> 5218
    //   4844: iload 17
    //   4846: ifeq +372 -> 5218
    //   4849: aload_3
    //   4850: astore 7
    //   4852: aload_3
    //   4853: astore 6
    //   4855: aload_3
    //   4856: astore 9
    //   4858: aload 8
    //   4860: aconst_null
    //   4861: ldc_w 458
    //   4864: invokeinterface 306 3 0
    //   4869: astore 14
    //   4871: aload 14
    //   4873: ifnonnull +128 -> 5001
    //   4876: aload_3
    //   4877: astore 7
    //   4879: aload_3
    //   4880: astore 6
    //   4882: aload_3
    //   4883: astore 9
    //   4885: new 263	java/lang/StringBuilder
    //   4888: astore 14
    //   4890: aload_3
    //   4891: astore 7
    //   4893: aload_3
    //   4894: astore 6
    //   4896: aload_3
    //   4897: astore 9
    //   4899: aload 14
    //   4901: invokespecial 264	java/lang/StringBuilder:<init>	()V
    //   4904: aload_3
    //   4905: astore 7
    //   4907: aload_3
    //   4908: astore 6
    //   4910: aload_3
    //   4911: astore 9
    //   4913: aload 14
    //   4915: ldc_w 460
    //   4918: invokevirtual 270	java/lang/StringBuilder:append	(Ljava/lang/String;)Ljava/lang/StringBuilder;
    //   4921: pop
    //   4922: aload_3
    //   4923: astore 7
    //   4925: aload_3
    //   4926: astore 6
    //   4928: aload_3
    //   4929: astore 9
    //   4931: aload 14
    //   4933: aload_1
    //   4934: invokevirtual 273	java/lang/StringBuilder:append	(Ljava/lang/Object;)Ljava/lang/StringBuilder;
    //   4937: pop
    //   4938: aload_3
    //   4939: astore 7
    //   4941: aload_3
    //   4942: astore 6
    //   4944: aload_3
    //   4945: astore 9
    //   4947: aload 14
    //   4949: ldc_w 324
    //   4952: invokevirtual 270	java/lang/StringBuilder:append	(Ljava/lang/String;)Ljava/lang/StringBuilder;
    //   4955: pop
    //   4956: aload_3
    //   4957: astore 7
    //   4959: aload_3
    //   4960: astore 6
    //   4962: aload_3
    //   4963: astore 9
    //   4965: aload 14
    //   4967: aload 8
    //   4969: invokeinterface 327 1 0
    //   4974: invokevirtual 270	java/lang/StringBuilder:append	(Ljava/lang/String;)Ljava/lang/StringBuilder;
    //   4977: pop
    //   4978: aload_3
    //   4979: astore 7
    //   4981: aload_3
    //   4982: astore 6
    //   4984: aload_3
    //   4985: astore 9
    //   4987: ldc 28
    //   4989: aload 14
    //   4991: invokevirtual 280	java/lang/StringBuilder:toString	()Ljava/lang/String;
    //   4994: invokestatic 333	android/util/Slog:w	(Ljava/lang/String;Ljava/lang/String;)I
    //   4997: pop
    //   4998: goto +203 -> 5201
    //   5001: aload_3
    //   5002: astore 7
    //   5004: aload_3
    //   5005: astore 6
    //   5007: aload_3
    //   5008: astore 9
    //   5010: aload 14
    //   5012: invokestatic 464	android/content/ComponentName:unflattenFromString	(Ljava/lang/String;)Landroid/content/ComponentName;
    //   5015: astore 22
    //   5017: aload 22
    //   5019: ifnonnull +163 -> 5182
    //   5022: aload_3
    //   5023: astore 7
    //   5025: aload_3
    //   5026: astore 6
    //   5028: aload_3
    //   5029: astore 9
    //   5031: new 263	java/lang/StringBuilder
    //   5034: astore 22
    //   5036: aload_3
    //   5037: astore 7
    //   5039: aload_3
    //   5040: astore 6
    //   5042: aload_3
    //   5043: astore 9
    //   5045: aload 22
    //   5047: invokespecial 264	java/lang/StringBuilder:<init>	()V
    //   5050: aload_3
    //   5051: astore 7
    //   5053: aload_3
    //   5054: astore 6
    //   5056: aload_3
    //   5057: astore 9
    //   5059: aload 22
    //   5061: ldc_w 466
    //   5064: invokevirtual 270	java/lang/StringBuilder:append	(Ljava/lang/String;)Ljava/lang/StringBuilder;
    //   5067: pop
    //   5068: aload_3
    //   5069: astore 7
    //   5071: aload_3
    //   5072: astore 6
    //   5074: aload_3
    //   5075: astore 9
    //   5077: aload 22
    //   5079: aload 14
    //   5081: invokevirtual 270	java/lang/StringBuilder:append	(Ljava/lang/String;)Ljava/lang/StringBuilder;
    //   5084: pop
    //   5085: aload_3
    //   5086: astore 7
    //   5088: aload_3
    //   5089: astore 6
    //   5091: aload_3
    //   5092: astore 9
    //   5094: aload 22
    //   5096: ldc_w 468
    //   5099: invokevirtual 270	java/lang/StringBuilder:append	(Ljava/lang/String;)Ljava/lang/StringBuilder;
    //   5102: pop
    //   5103: aload_3
    //   5104: astore 7
    //   5106: aload_3
    //   5107: astore 6
    //   5109: aload_3
    //   5110: astore 9
    //   5112: aload 22
    //   5114: aload_1
    //   5115: invokevirtual 273	java/lang/StringBuilder:append	(Ljava/lang/Object;)Ljava/lang/StringBuilder;
    //   5118: pop
    //   5119: aload_3
    //   5120: astore 7
    //   5122: aload_3
    //   5123: astore 6
    //   5125: aload_3
    //   5126: astore 9
    //   5128: aload 22
    //   5130: ldc_w 324
    //   5133: invokevirtual 270	java/lang/StringBuilder:append	(Ljava/lang/String;)Ljava/lang/StringBuilder;
    //   5136: pop
    //   5137: aload_3
    //   5138: astore 7
    //   5140: aload_3
    //   5141: astore 6
    //   5143: aload_3
    //   5144: astore 9
    //   5146: aload 22
    //   5148: aload 8
    //   5150: invokeinterface 327 1 0
    //   5155: invokevirtual 270	java/lang/StringBuilder:append	(Ljava/lang/String;)Ljava/lang/StringBuilder;
    //   5158: pop
    //   5159: aload_3
    //   5160: astore 7
    //   5162: aload_3
    //   5163: astore 6
    //   5165: aload_3
    //   5166: astore 9
    //   5168: ldc 28
    //   5170: aload 22
    //   5172: invokevirtual 280	java/lang/StringBuilder:toString	()Ljava/lang/String;
    //   5175: invokestatic 333	android/util/Slog:w	(Ljava/lang/String;Ljava/lang/String;)I
    //   5178: pop
    //   5179: goto +22 -> 5201
    //   5182: aload_3
    //   5183: astore 7
    //   5185: aload_3
    //   5186: astore 6
    //   5188: aload_3
    //   5189: astore 9
    //   5191: aload_0
    //   5192: getfield 112	com/android/server/SystemConfig:mBackupTransportWhitelist	Landroid/util/ArraySet;
    //   5195: aload 22
    //   5197: invokevirtual 372	android/util/ArraySet:add	(Ljava/lang/Object;)Z
    //   5200: pop
    //   5201: aload_3
    //   5202: astore 7
    //   5204: aload_3
    //   5205: astore 6
    //   5207: aload_3
    //   5208: astore 9
    //   5210: aload 8
    //   5212: invokestatic 336	com/android/internal/util/XmlUtils:skipCurrentTag	(Lorg/xmlpull/v1/XmlPullParser;)V
    //   5215: goto -1230 -> 3985
    //   5218: aload_3
    //   5219: astore 7
    //   5221: aload_3
    //   5222: astore 6
    //   5224: aload_3
    //   5225: astore 9
    //   5227: ldc_w 470
    //   5230: aload 14
    //   5232: invokevirtual 259	java/lang/String:equals	(Ljava/lang/Object;)Z
    //   5235: ifeq +307 -> 5542
    //   5238: iload 18
    //   5240: ifeq +302 -> 5542
    //   5243: aload_3
    //   5244: astore 7
    //   5246: aload_3
    //   5247: astore 6
    //   5249: aload_3
    //   5250: astore 9
    //   5252: aload 8
    //   5254: aconst_null
    //   5255: ldc_w 409
    //   5258: invokeinterface 306 3 0
    //   5263: astore 24
    //   5265: aload_3
    //   5266: astore 7
    //   5268: aload_3
    //   5269: astore 6
    //   5271: aload_3
    //   5272: astore 9
    //   5274: aload 8
    //   5276: aconst_null
    //   5277: ldc_w 472
    //   5280: invokeinterface 306 3 0
    //   5285: astore 23
    //   5287: aload 24
    //   5289: ifnull +114 -> 5403
    //   5292: aload 23
    //   5294: ifnonnull +6 -> 5300
    //   5297: goto +106 -> 5403
    //   5300: aload_3
    //   5301: astore 7
    //   5303: aload_3
    //   5304: astore 6
    //   5306: aload_3
    //   5307: astore 9
    //   5309: aload_0
    //   5310: getfield 118	com/android/server/SystemConfig:mDisabledUntilUsedPreinstalledCarrierAssociatedApps	Landroid/util/ArrayMap;
    //   5313: aload 23
    //   5315: invokevirtual 193	android/util/ArrayMap:get	(Ljava/lang/Object;)Ljava/lang/Object;
    //   5318: checkcast 474	java/util/List
    //   5321: astore 22
    //   5323: aload 22
    //   5325: astore 14
    //   5327: aload 22
    //   5329: ifnonnull +52 -> 5381
    //   5332: aload_3
    //   5333: astore 7
    //   5335: aload_3
    //   5336: astore 6
    //   5338: aload_3
    //   5339: astore 9
    //   5341: new 476	java/util/ArrayList
    //   5344: astore 14
    //   5346: aload_3
    //   5347: astore 7
    //   5349: aload_3
    //   5350: astore 6
    //   5352: aload_3
    //   5353: astore 9
    //   5355: aload 14
    //   5357: invokespecial 477	java/util/ArrayList:<init>	()V
    //   5360: aload_3
    //   5361: astore 7
    //   5363: aload_3
    //   5364: astore 6
    //   5366: aload_3
    //   5367: astore 9
    //   5369: aload_0
    //   5370: getfield 118	com/android/server/SystemConfig:mDisabledUntilUsedPreinstalledCarrierAssociatedApps	Landroid/util/ArrayMap;
    //   5373: aload 23
    //   5375: aload 14
    //   5377: invokevirtual 206	android/util/ArrayMap:put	(Ljava/lang/Object;Ljava/lang/Object;)Ljava/lang/Object;
    //   5380: pop
    //   5381: aload_3
    //   5382: astore 7
    //   5384: aload_3
    //   5385: astore 6
    //   5387: aload_3
    //   5388: astore 9
    //   5390: aload 14
    //   5392: aload 24
    //   5394: invokeinterface 478 2 0
    //   5399: pop
    //   5400: goto +125 -> 5525
    //   5403: aload_3
    //   5404: astore 7
    //   5406: aload_3
    //   5407: astore 6
    //   5409: aload_3
    //   5410: astore 9
    //   5412: new 263	java/lang/StringBuilder
    //   5415: astore 14
    //   5417: aload_3
    //   5418: astore 7
    //   5420: aload_3
    //   5421: astore 6
    //   5423: aload_3
    //   5424: astore 9
    //   5426: aload 14
    //   5428: invokespecial 264	java/lang/StringBuilder:<init>	()V
    //   5431: aload_3
    //   5432: astore 7
    //   5434: aload_3
    //   5435: astore 6
    //   5437: aload_3
    //   5438: astore 9
    //   5440: aload 14
    //   5442: ldc_w 480
    //   5445: invokevirtual 270	java/lang/StringBuilder:append	(Ljava/lang/String;)Ljava/lang/StringBuilder;
    //   5448: pop
    //   5449: aload_3
    //   5450: astore 7
    //   5452: aload_3
    //   5453: astore 6
    //   5455: aload_3
    //   5456: astore 9
    //   5458: aload 14
    //   5460: aload_1
    //   5461: invokevirtual 273	java/lang/StringBuilder:append	(Ljava/lang/Object;)Ljava/lang/StringBuilder;
    //   5464: pop
    //   5465: aload_3
    //   5466: astore 7
    //   5468: aload_3
    //   5469: astore 6
    //   5471: aload_3
    //   5472: astore 9
    //   5474: aload 14
    //   5476: ldc_w 324
    //   5479: invokevirtual 270	java/lang/StringBuilder:append	(Ljava/lang/String;)Ljava/lang/StringBuilder;
    //   5482: pop
    //   5483: aload_3
    //   5484: astore 7
    //   5486: aload_3
    //   5487: astore 6
    //   5489: aload_3
    //   5490: astore 9
    //   5492: aload 14
    //   5494: aload 8
    //   5496: invokeinterface 327 1 0
    //   5501: invokevirtual 270	java/lang/StringBuilder:append	(Ljava/lang/String;)Ljava/lang/StringBuilder;
    //   5504: pop
    //   5505: aload_3
    //   5506: astore 7
    //   5508: aload_3
    //   5509: astore 6
    //   5511: aload_3
    //   5512: astore 9
    //   5514: ldc 28
    //   5516: aload 14
    //   5518: invokevirtual 280	java/lang/StringBuilder:toString	()Ljava/lang/String;
    //   5521: invokestatic 333	android/util/Slog:w	(Ljava/lang/String;Ljava/lang/String;)I
    //   5524: pop
    //   5525: aload_3
    //   5526: astore 7
    //   5528: aload_3
    //   5529: astore 6
    //   5531: aload_3
    //   5532: astore 9
    //   5534: aload 8
    //   5536: invokestatic 336	com/android/internal/util/XmlUtils:skipCurrentTag	(Lorg/xmlpull/v1/XmlPullParser;)V
    //   5539: goto -1554 -> 3985
    //   5542: aload_3
    //   5543: astore 7
    //   5545: aload_3
    //   5546: astore 6
    //   5548: aload_3
    //   5549: astore 9
    //   5551: ldc_w 482
    //   5554: aload 14
    //   5556: invokevirtual 259	java/lang/String:equals	(Ljava/lang/Object;)Z
    //   5559: ifeq +196 -> 5755
    //   5562: iload 18
    //   5564: ifeq +191 -> 5755
    //   5567: aload_3
    //   5568: astore 7
    //   5570: aload_3
    //   5571: astore 6
    //   5573: aload_3
    //   5574: astore 9
    //   5576: aload 8
    //   5578: aconst_null
    //   5579: ldc_w 409
    //   5582: invokeinterface 306 3 0
    //   5587: astore 14
    //   5589: aload 14
    //   5591: ifnonnull +128 -> 5719
    //   5594: aload_3
    //   5595: astore 7
    //   5597: aload_3
    //   5598: astore 6
    //   5600: aload_3
    //   5601: astore 9
    //   5603: new 263	java/lang/StringBuilder
    //   5606: astore 14
    //   5608: aload_3
    //   5609: astore 7
    //   5611: aload_3
    //   5612: astore 6
    //   5614: aload_3
    //   5615: astore 9
    //   5617: aload 14
    //   5619: invokespecial 264	java/lang/StringBuilder:<init>	()V
    //   5622: aload_3
    //   5623: astore 7
    //   5625: aload_3
    //   5626: astore 6
    //   5628: aload_3
    //   5629: astore 9
    //   5631: aload 14
    //   5633: ldc_w 484
    //   5636: invokevirtual 270	java/lang/StringBuilder:append	(Ljava/lang/String;)Ljava/lang/StringBuilder;
    //   5639: pop
    //   5640: aload_3
    //   5641: astore 7
    //   5643: aload_3
    //   5644: astore 6
    //   5646: aload_3
    //   5647: astore 9
    //   5649: aload 14
    //   5651: aload_1
    //   5652: invokevirtual 273	java/lang/StringBuilder:append	(Ljava/lang/Object;)Ljava/lang/StringBuilder;
    //   5655: pop
    //   5656: aload_3
    //   5657: astore 7
    //   5659: aload_3
    //   5660: astore 6
    //   5662: aload_3
    //   5663: astore 9
    //   5665: aload 14
    //   5667: ldc_w 324
    //   5670: invokevirtual 270	java/lang/StringBuilder:append	(Ljava/lang/String;)Ljava/lang/StringBuilder;
    //   5673: pop
    //   5674: aload_3
    //   5675: astore 7
    //   5677: aload_3
    //   5678: astore 6
    //   5680: aload_3
    //   5681: astore 9
    //   5683: aload 14
    //   5685: aload 8
    //   5687: invokeinterface 327 1 0
    //   5692: invokevirtual 270	java/lang/StringBuilder:append	(Ljava/lang/String;)Ljava/lang/StringBuilder;
    //   5695: pop
    //   5696: aload_3
    //   5697: astore 7
    //   5699: aload_3
    //   5700: astore 6
    //   5702: aload_3
    //   5703: astore 9
    //   5705: ldc 28
    //   5707: aload 14
    //   5709: invokevirtual 280	java/lang/StringBuilder:toString	()Ljava/lang/String;
    //   5712: invokestatic 333	android/util/Slog:w	(Ljava/lang/String;Ljava/lang/String;)I
    //   5715: pop
    //   5716: goto +22 -> 5738
    //   5719: aload_3
    //   5720: astore 7
    //   5722: aload_3
    //   5723: astore 6
    //   5725: aload_3
    //   5726: astore 9
    //   5728: aload_0
    //   5729: getfield 116	com/android/server/SystemConfig:mDisabledUntilUsedPreinstalledCarrierApps	Landroid/util/ArraySet;
    //   5732: aload 14
    //   5734: invokevirtual 372	android/util/ArraySet:add	(Ljava/lang/Object;)Z
    //   5737: pop
    //   5738: aload_3
    //   5739: astore 7
    //   5741: aload_3
    //   5742: astore 6
    //   5744: aload_3
    //   5745: astore 9
    //   5747: aload 8
    //   5749: invokestatic 336	com/android/internal/util/XmlUtils:skipCurrentTag	(Lorg/xmlpull/v1/XmlPullParser;)V
    //   5752: goto -1767 -> 3985
    //   5755: aload_3
    //   5756: astore 7
    //   5758: aload_3
    //   5759: astore 6
    //   5761: aload_3
    //   5762: astore 9
    //   5764: ldc_w 486
    //   5767: aload 14
    //   5769: invokevirtual 259	java/lang/String:equals	(Ljava/lang/Object;)Z
    //   5772: ifeq +188 -> 5960
    //   5775: iload 19
    //   5777: ifeq +183 -> 5960
    //   5780: aload_3
    //   5781: astore 7
    //   5783: aload_3
    //   5784: astore 6
    //   5786: aload_3
    //   5787: astore 9
    //   5789: aload_1
    //   5790: invokevirtual 492	java/io/File:toPath	()Ljava/nio/file/Path;
    //   5793: invokestatic 162	android/os/Environment:getVendorDirectory	()Ljava/io/File;
    //   5796: invokevirtual 492	java/io/File:toPath	()Ljava/nio/file/Path;
    //   5799: invokeinterface 497 2 0
    //   5804: ifne +39 -> 5843
    //   5807: aload_3
    //   5808: astore 7
    //   5810: aload_3
    //   5811: astore 6
    //   5813: aload_3
    //   5814: astore 9
    //   5816: aload_1
    //   5817: invokevirtual 492	java/io/File:toPath	()Ljava/nio/file/Path;
    //   5820: invokestatic 165	android/os/Environment:getOdmDirectory	()Ljava/io/File;
    //   5823: invokevirtual 492	java/io/File:toPath	()Ljava/nio/file/Path;
    //   5826: invokeinterface 497 2 0
    //   5831: ifeq +6 -> 5837
    //   5834: goto +9 -> 5843
    //   5837: iconst_0
    //   5838: istore 12
    //   5840: goto +6 -> 5846
    //   5843: iconst_1
    //   5844: istore 12
    //   5846: aload_3
    //   5847: astore 7
    //   5849: aload_3
    //   5850: astore 6
    //   5852: aload_3
    //   5853: astore 9
    //   5855: aload_1
    //   5856: invokevirtual 492	java/io/File:toPath	()Ljava/nio/file/Path;
    //   5859: invokestatic 171	android/os/Environment:getProductDirectory	()Ljava/io/File;
    //   5862: invokevirtual 492	java/io/File:toPath	()Ljava/nio/file/Path;
    //   5865: invokeinterface 497 2 0
    //   5870: istore 13
    //   5872: iload 12
    //   5874: ifeq +29 -> 5903
    //   5877: aload_3
    //   5878: astore 7
    //   5880: aload_3
    //   5881: astore 6
    //   5883: aload_3
    //   5884: astore 9
    //   5886: aload_0
    //   5887: aload 8
    //   5889: aload_0
    //   5890: getfield 124	com/android/server/SystemConfig:mVendorPrivAppPermissions	Landroid/util/ArrayMap;
    //   5893: aload_0
    //   5894: getfield 126	com/android/server/SystemConfig:mVendorPrivAppDenyPermissions	Landroid/util/ArrayMap;
    //   5897: invokespecial 501	com/android/server/SystemConfig:readPrivAppPermissions	(Lorg/xmlpull/v1/XmlPullParser;Landroid/util/ArrayMap;Landroid/util/ArrayMap;)V
    //   5900: goto +57 -> 5957
    //   5903: iload 13
    //   5905: ifeq +29 -> 5934
    //   5908: aload_3
    //   5909: astore 7
    //   5911: aload_3
    //   5912: astore 6
    //   5914: aload_3
    //   5915: astore 9
    //   5917: aload_0
    //   5918: aload 8
    //   5920: aload_0
    //   5921: getfield 128	com/android/server/SystemConfig:mProductPrivAppPermissions	Landroid/util/ArrayMap;
    //   5924: aload_0
    //   5925: getfield 130	com/android/server/SystemConfig:mProductPrivAppDenyPermissions	Landroid/util/ArrayMap;
    //   5928: invokespecial 501	com/android/server/SystemConfig:readPrivAppPermissions	(Lorg/xmlpull/v1/XmlPullParser;Landroid/util/ArrayMap;Landroid/util/ArrayMap;)V
    //   5931: goto +26 -> 5957
    //   5934: aload_3
    //   5935: astore 7
    //   5937: aload_3
    //   5938: astore 6
    //   5940: aload_3
    //   5941: astore 9
    //   5943: aload_0
    //   5944: aload 8
    //   5946: aload_0
    //   5947: getfield 120	com/android/server/SystemConfig:mPrivAppPermissions	Landroid/util/ArrayMap;
    //   5950: aload_0
    //   5951: getfield 122	com/android/server/SystemConfig:mPrivAppDenyPermissions	Landroid/util/ArrayMap;
    //   5954: invokespecial 501	com/android/server/SystemConfig:readPrivAppPermissions	(Lorg/xmlpull/v1/XmlPullParser;Landroid/util/ArrayMap;Landroid/util/ArrayMap;)V
    //   5957: goto -1972 -> 3985
    //   5960: aload_3
    //   5961: astore 7
    //   5963: aload_3
    //   5964: astore 6
    //   5966: aload_3
    //   5967: astore 9
    //   5969: ldc_w 503
    //   5972: aload 14
    //   5974: invokevirtual 259	java/lang/String:equals	(Ljava/lang/Object;)Z
    //   5977: ifeq +26 -> 6003
    //   5980: iload 20
    //   5982: ifeq +21 -> 6003
    //   5985: aload_3
    //   5986: astore 7
    //   5988: aload_3
    //   5989: astore 6
    //   5991: aload_3
    //   5992: astore 9
    //   5994: aload_0
    //   5995: aload 8
    //   5997: invokevirtual 506	com/android/server/SystemConfig:readOemPermissions	(Lorg/xmlpull/v1/XmlPullParser;)V
    //   6000: goto -2015 -> 3985
    //   6003: aload_3
    //   6004: astore 7
    //   6006: aload_3
    //   6007: astore 6
    //   6009: aload_3
    //   6010: astore 9
    //   6012: ldc_w 508
    //   6015: aload 14
    //   6017: invokevirtual 259	java/lang/String:equals	(Ljava/lang/Object;)Z
    //   6020: ifeq +195 -> 6215
    //   6023: iload_2
    //   6024: ifeq +191 -> 6215
    //   6027: aload_3
    //   6028: astore 7
    //   6030: aload_3
    //   6031: astore 6
    //   6033: aload_3
    //   6034: astore 9
    //   6036: aload 8
    //   6038: aconst_null
    //   6039: ldc_w 409
    //   6042: invokeinterface 306 3 0
    //   6047: astore 14
    //   6049: aload 14
    //   6051: ifnonnull +128 -> 6179
    //   6054: aload_3
    //   6055: astore 7
    //   6057: aload_3
    //   6058: astore 6
    //   6060: aload_3
    //   6061: astore 9
    //   6063: new 263	java/lang/StringBuilder
    //   6066: astore 14
    //   6068: aload_3
    //   6069: astore 7
    //   6071: aload_3
    //   6072: astore 6
    //   6074: aload_3
    //   6075: astore 9
    //   6077: aload 14
    //   6079: invokespecial 264	java/lang/StringBuilder:<init>	()V
    //   6082: aload_3
    //   6083: astore 7
    //   6085: aload_3
    //   6086: astore 6
    //   6088: aload_3
    //   6089: astore 9
    //   6091: aload 14
    //   6093: ldc_w 510
    //   6096: invokevirtual 270	java/lang/StringBuilder:append	(Ljava/lang/String;)Ljava/lang/StringBuilder;
    //   6099: pop
    //   6100: aload_3
    //   6101: astore 7
    //   6103: aload_3
    //   6104: astore 6
    //   6106: aload_3
    //   6107: astore 9
    //   6109: aload 14
    //   6111: aload_1
    //   6112: invokevirtual 273	java/lang/StringBuilder:append	(Ljava/lang/Object;)Ljava/lang/StringBuilder;
    //   6115: pop
    //   6116: aload_3
    //   6117: astore 7
    //   6119: aload_3
    //   6120: astore 6
    //   6122: aload_3
    //   6123: astore 9
    //   6125: aload 14
    //   6127: ldc_w 324
    //   6130: invokevirtual 270	java/lang/StringBuilder:append	(Ljava/lang/String;)Ljava/lang/StringBuilder;
    //   6133: pop
    //   6134: aload_3
    //   6135: astore 7
    //   6137: aload_3
    //   6138: astore 6
    //   6140: aload_3
    //   6141: astore 9
    //   6143: aload 14
    //   6145: aload 8
    //   6147: invokeinterface 327 1 0
    //   6152: invokevirtual 270	java/lang/StringBuilder:append	(Ljava/lang/String;)Ljava/lang/StringBuilder;
    //   6155: pop
    //   6156: aload_3
    //   6157: astore 7
    //   6159: aload_3
    //   6160: astore 6
    //   6162: aload_3
    //   6163: astore 9
    //   6165: ldc 28
    //   6167: aload 14
    //   6169: invokevirtual 280	java/lang/StringBuilder:toString	()Ljava/lang/String;
    //   6172: invokestatic 333	android/util/Slog:w	(Ljava/lang/String;Ljava/lang/String;)I
    //   6175: pop
    //   6176: goto +22 -> 6198
    //   6179: aload_3
    //   6180: astore 7
    //   6182: aload_3
    //   6183: astore 6
    //   6185: aload_3
    //   6186: astore 9
    //   6188: aload_0
    //   6189: getfield 114	com/android/server/SystemConfig:mHiddenApiPackageWhitelist	Landroid/util/ArraySet;
    //   6192: aload 14
    //   6194: invokevirtual 372	android/util/ArraySet:add	(Ljava/lang/Object;)Z
    //   6197: pop
    //   6198: aload_3
    //   6199: astore 7
    //   6201: aload_3
    //   6202: astore 6
    //   6204: aload_3
    //   6205: astore 9
    //   6207: aload 8
    //   6209: invokestatic 336	com/android/internal/util/XmlUtils:skipCurrentTag	(Lorg/xmlpull/v1/XmlPullParser;)V
    //   6212: goto +137 -> 6349
    //   6215: aload_3
    //   6216: astore 7
    //   6218: aload_3
    //   6219: astore 6
    //   6221: aload_3
    //   6222: astore 9
    //   6224: new 263	java/lang/StringBuilder
    //   6227: astore 22
    //   6229: aload_3
    //   6230: astore 7
    //   6232: aload_3
    //   6233: astore 6
    //   6235: aload_3
    //   6236: astore 9
    //   6238: aload 22
    //   6240: invokespecial 264	java/lang/StringBuilder:<init>	()V
    //   6243: aload_3
    //   6244: astore 7
    //   6246: aload_3
    //   6247: astore 6
    //   6249: aload_3
    //   6250: astore 9
    //   6252: aload 22
    //   6254: ldc_w 512
    //   6257: invokevirtual 270	java/lang/StringBuilder:append	(Ljava/lang/String;)Ljava/lang/StringBuilder;
    //   6260: pop
    //   6261: aload_3
    //   6262: astore 7
    //   6264: aload_3
    //   6265: astore 6
    //   6267: aload_3
    //   6268: astore 9
    //   6270: aload 22
    //   6272: aload 14
    //   6274: invokevirtual 270	java/lang/StringBuilder:append	(Ljava/lang/String;)Ljava/lang/StringBuilder;
    //   6277: pop
    //   6278: aload_3
    //   6279: astore 7
    //   6281: aload_3
    //   6282: astore 6
    //   6284: aload_3
    //   6285: astore 9
    //   6287: aload 22
    //   6289: ldc_w 514
    //   6292: invokevirtual 270	java/lang/StringBuilder:append	(Ljava/lang/String;)Ljava/lang/StringBuilder;
    //   6295: pop
    //   6296: aload_3
    //   6297: astore 7
    //   6299: aload_3
    //   6300: astore 6
    //   6302: aload_3
    //   6303: astore 9
    //   6305: aload 22
    //   6307: aload_1
    //   6308: invokevirtual 517	java/io/File:getParent	()Ljava/lang/String;
    //   6311: invokevirtual 270	java/lang/StringBuilder:append	(Ljava/lang/String;)Ljava/lang/StringBuilder;
    //   6314: pop
    //   6315: aload_3
    //   6316: astore 7
    //   6318: aload_3
    //   6319: astore 6
    //   6321: aload_3
    //   6322: astore 9
    //   6324: ldc 28
    //   6326: aload 22
    //   6328: invokevirtual 280	java/lang/StringBuilder:toString	()Ljava/lang/String;
    //   6331: invokestatic 333	android/util/Slog:w	(Ljava/lang/String;Ljava/lang/String;)I
    //   6334: pop
    //   6335: aload_3
    //   6336: astore 7
    //   6338: aload_3
    //   6339: astore 6
    //   6341: aload_3
    //   6342: astore 9
    //   6344: aload 8
    //   6346: invokestatic 336	com/android/internal/util/XmlUtils:skipCurrentTag	(Lorg/xmlpull/v1/XmlPullParser;)V
    //   6349: aconst_null
    //   6350: astore_3
    //   6351: iconst_1
    //   6352: istore 12
    //   6354: goto -5860 -> 494
    //   6357: aload 4
    //   6359: astore 7
    //   6361: aload 4
    //   6363: astore 6
    //   6365: aload 4
    //   6367: astore 9
    //   6369: new 222	org/xmlpull/v1/XmlPullParserException
    //   6372: astore_1
    //   6373: aload 4
    //   6375: astore 7
    //   6377: aload 4
    //   6379: astore 6
    //   6381: aload 4
    //   6383: astore 9
    //   6385: aload_1
    //   6386: ldc_w 519
    //   6389: invokespecial 283	org/xmlpull/v1/XmlPullParserException:<init>	(Ljava/lang/String;)V
    //   6392: aload 4
    //   6394: astore 7
    //   6396: aload 4
    //   6398: astore 6
    //   6400: aload 4
    //   6402: astore 9
    //   6404: aload_1
    //   6405: athrow
    //   6406: astore_1
    //   6407: aload 7
    //   6409: astore 4
    //   6411: goto +192 -> 6603
    //   6414: astore_1
    //   6415: goto +32 -> 6447
    //   6418: astore 4
    //   6420: aload 9
    //   6422: astore_1
    //   6423: goto +59 -> 6482
    //   6426: astore 4
    //   6428: aload 9
    //   6430: astore_1
    //   6431: goto +51 -> 6482
    //   6434: astore_1
    //   6435: aload 6
    //   6437: astore 4
    //   6439: goto +164 -> 6603
    //   6442: astore_1
    //   6443: aload 7
    //   6445: astore 6
    //   6447: ldc 28
    //   6449: ldc_w 521
    //   6452: aload_1
    //   6453: invokestatic 524	android/util/Slog:w	(Ljava/lang/String;Ljava/lang/String;Ljava/lang/Throwable;)I
    //   6456: pop
    //   6457: aload 6
    //   6459: invokestatic 298	libcore/io/IoUtils:closeQuietly	(Ljava/lang/AutoCloseable;)V
    //   6462: goto +35 -> 6497
    //   6465: astore_1
    //   6466: aload 6
    //   6468: astore 4
    //   6470: goto +133 -> 6603
    //   6473: astore 6
    //   6475: aload 4
    //   6477: astore_1
    //   6478: aload 6
    //   6480: astore 4
    //   6482: ldc 28
    //   6484: ldc_w 521
    //   6487: aload 4
    //   6489: invokestatic 524	android/util/Slog:w	(Ljava/lang/String;Ljava/lang/String;Ljava/lang/Throwable;)I
    //   6492: pop
    //   6493: aload_1
    //   6494: invokestatic 298	libcore/io/IoUtils:closeQuietly	(Ljava/lang/AutoCloseable;)V
    //   6497: invokestatic 529	android/os/storage/StorageManager:isFileEncryptedNativeOnly	()Z
    //   6500: ifeq +22 -> 6522
    //   6503: aload_0
    //   6504: ldc_w 531
    //   6507: iconst_0
    //   6508: invokespecial 188	com/android/server/SystemConfig:addFeature	(Ljava/lang/String;I)V
    //   6511: aload_0
    //   6512: ldc_w 533
    //   6515: iconst_0
    //   6516: invokespecial 188	com/android/server/SystemConfig:addFeature	(Ljava/lang/String;I)V
    //   6519: goto +3 -> 6522
    //   6522: invokestatic 536	android/os/storage/StorageManager:hasAdoptable	()Z
    //   6525: ifeq +11 -> 6536
    //   6528: aload_0
    //   6529: ldc_w 538
    //   6532: iconst_0
    //   6533: invokespecial 188	com/android/server/SystemConfig:addFeature	(Ljava/lang/String;I)V
    //   6536: invokestatic 235	android/app/ActivityManager:isLowRamDeviceStatic	()Z
    //   6539: ifeq +14 -> 6553
    //   6542: aload_0
    //   6543: ldc_w 540
    //   6546: iconst_0
    //   6547: invokespecial 188	com/android/server/SystemConfig:addFeature	(Ljava/lang/String;I)V
    //   6550: goto +11 -> 6561
    //   6553: aload_0
    //   6554: ldc_w 542
    //   6557: iconst_0
    //   6558: invokespecial 188	com/android/server/SystemConfig:addFeature	(Ljava/lang/String;I)V
    //   6561: aload_0
    //   6562: getfield 90	com/android/server/SystemConfig:mUnavailableFeatures	Landroid/util/ArraySet;
    //   6565: invokevirtual 546	android/util/ArraySet:iterator	()Ljava/util/Iterator;
    //   6568: astore_1
    //   6569: aload_1
    //   6570: invokeinterface 551 1 0
    //   6575: ifeq +19 -> 6594
    //   6578: aload_0
    //   6579: aload_1
    //   6580: invokeinterface 554 1 0
    //   6585: checkcast 140	java/lang/String
    //   6588: invokespecial 557	com/android/server/SystemConfig:removeFeature	(Ljava/lang/String;)V
    //   6591: goto -22 -> 6569
    //   6594: return
    //   6595: astore 6
    //   6597: aload_1
    //   6598: astore 4
    //   6600: aload 6
    //   6602: astore_1
    //   6603: aload 4
    //   6605: invokestatic 298	libcore/io/IoUtils:closeQuietly	(Ljava/lang/AutoCloseable;)V
    //   6608: aload_1
    //   6609: athrow
    //   6610: astore 4
    //   6612: new 263	java/lang/StringBuilder
    //   6615: dup
    //   6616: invokespecial 264	java/lang/StringBuilder:<init>	()V
    //   6619: astore 4
    //   6621: aload 4
    //   6623: ldc_w 559
    //   6626: invokevirtual 270	java/lang/StringBuilder:append	(Ljava/lang/String;)Ljava/lang/StringBuilder;
    //   6629: pop
    //   6630: aload 4
    //   6632: aload_1
    //   6633: invokevirtual 273	java/lang/StringBuilder:append	(Ljava/lang/Object;)Ljava/lang/StringBuilder;
    //   6636: pop
    //   6637: ldc 28
    //   6639: aload 4
    //   6641: invokevirtual 280	java/lang/StringBuilder:toString	()Ljava/lang/String;
    //   6644: invokestatic 333	android/util/Slog:w	(Ljava/lang/String;Ljava/lang/String;)I
    //   6647: pop
    //   6648: return
    // Local variable table:
    //   start	length	slot	name	signature
    //   0	6649	0	this	SystemConfig
    //   0	6649	1	paramFile	File
    //   0	6649	2	paramInt	int
    //   1	6350	3	localObject1	Object
    //   10	343	4	localObject2	Object
    //   365	6036	4	localXmlPullParserException1	XmlPullParserException
    //   6409	1	4	localObject3	Object
    //   6418	1	4	localXmlPullParserException2	XmlPullParserException
    //   6426	1	4	localXmlPullParserException3	XmlPullParserException
    //   6437	167	4	localObject4	Object
    //   6610	1	4	localFileNotFoundException	java.io.FileNotFoundException
    //   6619	21	4	localStringBuilder	StringBuilder
    //   15	2234	5	bool1	boolean
    //   19	6448	6	localObject5	Object
    //   6473	6	6	localXmlPullParserException4	XmlPullParserException
    //   6595	6	6	localObject6	Object
    //   23	6421	7	localObject7	Object
    //   28	6317	8	localXmlPullParser	XmlPullParser
    //   32	6397	9	localObject8	Object
    //   70	1025	10	i	int
    //   74	24	11	j	int
    //   77	2178	12	k	int
    //   2287	4066	12	bool2	boolean
    //   124	5780	13	bool3	boolean
    //   177	6096	14	localObject9	Object
    //   379	3204	15	m	int
    //   394	1441	16	n	int
    //   409	4436	17	i1	int
    //   440	5123	18	i2	int
    //   456	5320	19	i3	int
    //   472	5509	20	i4	int
    //   530	1943	21	i5	int
    //   1122	5205	22	localObject10	Object
    //   1695	3679	23	str	String
    //   4770	623	24	localObject11	Object
    // Exception table:
    //   from	to	target	type
    //   143	159	349	finally
    //   174	179	349	finally
    //   191	195	349	finally
    //   207	211	349	finally
    //   223	231	349	finally
    //   243	249	349	finally
    //   261	269	349	finally
    //   281	293	349	finally
    //   305	313	349	finally
    //   325	334	349	finally
    //   346	349	349	finally
    //   612	624	349	finally
    //   640	646	349	finally
    //   658	671	349	finally
    //   686	690	349	finally
    //   702	706	349	finally
    //   718	726	349	finally
    //   738	744	349	finally
    //   756	764	349	finally
    //   776	788	349	finally
    //   800	810	349	finally
    //   822	827	349	finally
    //   874	886	349	finally
    //   902	906	349	finally
    //   918	922	349	finally
    //   934	942	349	finally
    //   954	960	349	finally
    //   972	980	349	finally
    //   992	1004	349	finally
    //   1016	1026	349	finally
    //   1038	1043	349	finally
    //   1058	1068	349	finally
    //   1141	1145	349	finally
    //   1157	1161	349	finally
    //   1173	1181	349	finally
    //   1193	1199	349	finally
    //   1211	1219	349	finally
    //   1231	1243	349	finally
    //   1255	1265	349	finally
    //   1277	1282	349	finally
    //   1327	1331	349	finally
    //   1343	1347	349	finally
    //   1359	1367	349	finally
    //   1379	1385	349	finally
    //   1397	1405	349	finally
    //   1417	1429	349	finally
    //   1441	1451	349	finally
    //   1463	1468	349	finally
    //   143	159	357	java/io/IOException
    //   174	179	357	java/io/IOException
    //   191	195	357	java/io/IOException
    //   207	211	357	java/io/IOException
    //   223	231	357	java/io/IOException
    //   243	249	357	java/io/IOException
    //   261	269	357	java/io/IOException
    //   281	293	357	java/io/IOException
    //   305	313	357	java/io/IOException
    //   325	334	357	java/io/IOException
    //   346	349	357	java/io/IOException
    //   612	624	357	java/io/IOException
    //   640	646	357	java/io/IOException
    //   658	671	357	java/io/IOException
    //   686	690	357	java/io/IOException
    //   702	706	357	java/io/IOException
    //   718	726	357	java/io/IOException
    //   738	744	357	java/io/IOException
    //   756	764	357	java/io/IOException
    //   776	788	357	java/io/IOException
    //   800	810	357	java/io/IOException
    //   822	827	357	java/io/IOException
    //   874	886	357	java/io/IOException
    //   902	906	357	java/io/IOException
    //   918	922	357	java/io/IOException
    //   934	942	357	java/io/IOException
    //   954	960	357	java/io/IOException
    //   972	980	357	java/io/IOException
    //   992	1004	357	java/io/IOException
    //   1016	1026	357	java/io/IOException
    //   1038	1043	357	java/io/IOException
    //   1058	1068	357	java/io/IOException
    //   1141	1145	357	java/io/IOException
    //   1157	1161	357	java/io/IOException
    //   1173	1181	357	java/io/IOException
    //   1193	1199	357	java/io/IOException
    //   1211	1219	357	java/io/IOException
    //   1231	1243	357	java/io/IOException
    //   1255	1265	357	java/io/IOException
    //   1277	1282	357	java/io/IOException
    //   1327	1331	357	java/io/IOException
    //   1343	1347	357	java/io/IOException
    //   1359	1367	357	java/io/IOException
    //   1379	1385	357	java/io/IOException
    //   1397	1405	357	java/io/IOException
    //   1417	1429	357	java/io/IOException
    //   1441	1451	357	java/io/IOException
    //   1463	1468	357	java/io/IOException
    //   143	159	365	org/xmlpull/v1/XmlPullParserException
    //   174	179	365	org/xmlpull/v1/XmlPullParserException
    //   191	195	365	org/xmlpull/v1/XmlPullParserException
    //   207	211	365	org/xmlpull/v1/XmlPullParserException
    //   223	231	365	org/xmlpull/v1/XmlPullParserException
    //   243	249	365	org/xmlpull/v1/XmlPullParserException
    //   261	269	365	org/xmlpull/v1/XmlPullParserException
    //   281	293	365	org/xmlpull/v1/XmlPullParserException
    //   305	313	365	org/xmlpull/v1/XmlPullParserException
    //   325	334	365	org/xmlpull/v1/XmlPullParserException
    //   346	349	365	org/xmlpull/v1/XmlPullParserException
    //   612	624	365	org/xmlpull/v1/XmlPullParserException
    //   640	646	365	org/xmlpull/v1/XmlPullParserException
    //   658	671	365	org/xmlpull/v1/XmlPullParserException
    //   686	690	365	org/xmlpull/v1/XmlPullParserException
    //   702	706	365	org/xmlpull/v1/XmlPullParserException
    //   718	726	365	org/xmlpull/v1/XmlPullParserException
    //   738	744	365	org/xmlpull/v1/XmlPullParserException
    //   756	764	365	org/xmlpull/v1/XmlPullParserException
    //   776	788	365	org/xmlpull/v1/XmlPullParserException
    //   800	810	365	org/xmlpull/v1/XmlPullParserException
    //   822	827	365	org/xmlpull/v1/XmlPullParserException
    //   874	886	365	org/xmlpull/v1/XmlPullParserException
    //   902	906	365	org/xmlpull/v1/XmlPullParserException
    //   918	922	365	org/xmlpull/v1/XmlPullParserException
    //   934	942	365	org/xmlpull/v1/XmlPullParserException
    //   954	960	365	org/xmlpull/v1/XmlPullParserException
    //   972	980	365	org/xmlpull/v1/XmlPullParserException
    //   992	1004	365	org/xmlpull/v1/XmlPullParserException
    //   1016	1026	365	org/xmlpull/v1/XmlPullParserException
    //   1038	1043	365	org/xmlpull/v1/XmlPullParserException
    //   1058	1068	365	org/xmlpull/v1/XmlPullParserException
    //   1141	1145	365	org/xmlpull/v1/XmlPullParserException
    //   1157	1161	365	org/xmlpull/v1/XmlPullParserException
    //   1173	1181	365	org/xmlpull/v1/XmlPullParserException
    //   1193	1199	365	org/xmlpull/v1/XmlPullParserException
    //   1211	1219	365	org/xmlpull/v1/XmlPullParserException
    //   1231	1243	365	org/xmlpull/v1/XmlPullParserException
    //   1255	1265	365	org/xmlpull/v1/XmlPullParserException
    //   1277	1282	365	org/xmlpull/v1/XmlPullParserException
    //   1327	1331	365	org/xmlpull/v1/XmlPullParserException
    //   1343	1347	365	org/xmlpull/v1/XmlPullParserException
    //   1359	1367	365	org/xmlpull/v1/XmlPullParserException
    //   1379	1385	365	org/xmlpull/v1/XmlPullParserException
    //   1397	1405	365	org/xmlpull/v1/XmlPullParserException
    //   1417	1429	365	org/xmlpull/v1/XmlPullParserException
    //   1441	1451	365	org/xmlpull/v1/XmlPullParserException
    //   1463	1468	365	org/xmlpull/v1/XmlPullParserException
    //   1541	1550	6406	finally
    //   1559	1567	6406	finally
    //   1576	1585	6406	finally
    //   1594	1601	6406	finally
    //   1610	1619	6406	finally
    //   1628	1641	6406	finally
    //   1650	1661	6406	finally
    //   1670	1675	6406	finally
    //   1690	1697	6406	finally
    //   1706	1720	6406	finally
    //   1738	1743	6406	finally
    //   1752	1757	6406	finally
    //   1766	1777	6406	finally
    //   1786	1794	6406	finally
    //   1803	1808	6406	finally
    //   1823	1834	6406	finally
    //   1848	1861	6406	finally
    //   1870	1883	6406	finally
    //   1897	1902	6406	finally
    //   1911	1916	6406	finally
    //   1925	1934	6406	finally
    //   1943	1950	6406	finally
    //   1959	1968	6406	finally
    //   1977	1990	6406	finally
    //   1999	2010	6406	finally
    //   2027	2032	6406	finally
    //   2041	2046	6406	finally
    //   2055	2064	6406	finally
    //   2073	2080	6406	finally
    //   2089	2098	6406	finally
    //   2107	2120	6406	finally
    //   2129	2140	6406	finally
    //   2152	2164	6406	finally
    //   2173	2178	6406	finally
    //   2190	2201	6406	finally
    //   2215	2228	6406	finally
    //   2237	2248	6406	finally
    //   2268	2289	6406	finally
    //   2303	2308	6406	finally
    //   2317	2322	6406	finally
    //   2331	2340	6406	finally
    //   2349	2356	6406	finally
    //   2365	2374	6406	finally
    //   2383	2396	6406	finally
    //   2405	2416	6406	finally
    //   2433	2444	6406	finally
    //   2453	2457	6406	finally
    //   2469	2477	6406	finally
    //   2489	2494	6406	finally
    //   2506	2517	6406	finally
    //   2531	2544	6406	finally
    //   2558	2563	6406	finally
    //   2572	2577	6406	finally
    //   2586	2595	6406	finally
    //   2604	2611	6406	finally
    //   2620	2629	6406	finally
    //   2638	2651	6406	finally
    //   2660	2671	6406	finally
    //   2683	2693	6406	finally
    //   2702	2707	6406	finally
    //   2719	2730	6406	finally
    //   2744	2757	6406	finally
    //   2771	2776	6406	finally
    //   2785	2790	6406	finally
    //   2799	2808	6406	finally
    //   2817	2824	6406	finally
    //   2833	2842	6406	finally
    //   2851	2864	6406	finally
    //   2873	2884	6406	finally
    //   2896	2906	6406	finally
    //   2915	2920	6406	finally
    //   2932	2943	6406	finally
    //   2957	2970	6406	finally
    //   2984	2989	6406	finally
    //   2998	3003	6406	finally
    //   3012	3021	6406	finally
    //   3030	3037	6406	finally
    //   3046	3055	6406	finally
    //   3064	3077	6406	finally
    //   3086	3097	6406	finally
    //   3109	3119	6406	finally
    //   3128	3133	6406	finally
    //   3145	3156	6406	finally
    //   3170	3183	6406	finally
    //   3197	3202	6406	finally
    //   3211	3216	6406	finally
    //   3225	3234	6406	finally
    //   3243	3250	6406	finally
    //   3259	3268	6406	finally
    //   3277	3290	6406	finally
    //   3299	3310	6406	finally
    //   3322	3332	6406	finally
    //   3341	3346	6406	finally
    //   3358	3369	6406	finally
    //   3383	3396	6406	finally
    //   3410	3415	6406	finally
    //   3424	3429	6406	finally
    //   3438	3447	6406	finally
    //   3456	3463	6406	finally
    //   3472	3481	6406	finally
    //   3490	3503	6406	finally
    //   3512	3523	6406	finally
    //   3535	3545	6406	finally
    //   3554	3559	6406	finally
    //   3571	3582	6406	finally
    //   3596	3609	6406	finally
    //   3623	3628	6406	finally
    //   3637	3642	6406	finally
    //   3651	3660	6406	finally
    //   3669	3676	6406	finally
    //   3685	3694	6406	finally
    //   3703	3716	6406	finally
    //   3725	3736	6406	finally
    //   3748	3758	6406	finally
    //   3767	3772	6406	finally
    //   3784	3795	6406	finally
    //   3809	3822	6406	finally
    //   3836	3841	6406	finally
    //   3850	3855	6406	finally
    //   3864	3873	6406	finally
    //   3882	3889	6406	finally
    //   3898	3907	6406	finally
    //   3916	3929	6406	finally
    //   3938	3949	6406	finally
    //   3961	3971	6406	finally
    //   3980	3985	6406	finally
    //   3997	4008	6406	finally
    //   4022	4035	6406	finally
    //   4049	4054	6406	finally
    //   4063	4068	6406	finally
    //   4077	4086	6406	finally
    //   4095	4102	6406	finally
    //   4111	4120	6406	finally
    //   4129	4142	6406	finally
    //   4151	4162	6406	finally
    //   4174	4184	6406	finally
    //   4193	4198	6406	finally
    //   4210	4221	6406	finally
    //   4235	4248	6406	finally
    //   4262	4267	6406	finally
    //   4276	4281	6406	finally
    //   4290	4299	6406	finally
    //   4308	4315	6406	finally
    //   4324	4333	6406	finally
    //   4342	4355	6406	finally
    //   4364	4375	6406	finally
    //   4387	4397	6406	finally
    //   4406	4411	6406	finally
    //   4423	4434	6406	finally
    //   4448	4461	6406	finally
    //   4470	4483	6406	finally
    //   4497	4502	6406	finally
    //   4511	4516	6406	finally
    //   4525	4534	6406	finally
    //   4543	4550	6406	finally
    //   4559	4568	6406	finally
    //   4577	4590	6406	finally
    //   4599	4610	6406	finally
    //   4627	4632	6406	finally
    //   4641	4646	6406	finally
    //   4655	4664	6406	finally
    //   4673	4680	6406	finally
    //   4689	4698	6406	finally
    //   4707	4720	6406	finally
    //   4729	4740	6406	finally
    //   4752	4758	6406	finally
    //   4767	4772	6406	finally
    //   4781	4790	6406	finally
    //   4799	4807	6406	finally
    //   4816	4821	6406	finally
    //   4833	4844	6406	finally
    //   4858	4871	6406	finally
    //   4885	4890	6406	finally
    //   4899	4904	6406	finally
    //   4913	4922	6406	finally
    //   4931	4938	6406	finally
    //   4947	4956	6406	finally
    //   4965	4978	6406	finally
    //   4987	4998	6406	finally
    //   5010	5017	6406	finally
    //   5031	5036	6406	finally
    //   5045	5050	6406	finally
    //   5059	5068	6406	finally
    //   5077	5085	6406	finally
    //   5094	5103	6406	finally
    //   5112	5119	6406	finally
    //   5128	5137	6406	finally
    //   5146	5159	6406	finally
    //   5168	5179	6406	finally
    //   5191	5201	6406	finally
    //   5210	5215	6406	finally
    //   5227	5238	6406	finally
    //   5252	5265	6406	finally
    //   5274	5287	6406	finally
    //   5309	5323	6406	finally
    //   5341	5346	6406	finally
    //   5355	5360	6406	finally
    //   5369	5381	6406	finally
    //   5390	5400	6406	finally
    //   5412	5417	6406	finally
    //   5426	5431	6406	finally
    //   5440	5449	6406	finally
    //   5458	5465	6406	finally
    //   5474	5483	6406	finally
    //   5492	5505	6406	finally
    //   5514	5525	6406	finally
    //   5534	5539	6406	finally
    //   5551	5562	6406	finally
    //   5576	5589	6406	finally
    //   5603	5608	6406	finally
    //   5617	5622	6406	finally
    //   5631	5640	6406	finally
    //   5649	5656	6406	finally
    //   5665	5674	6406	finally
    //   5683	5696	6406	finally
    //   5705	5716	6406	finally
    //   5728	5738	6406	finally
    //   5747	5752	6406	finally
    //   5764	5775	6406	finally
    //   5789	5807	6406	finally
    //   5816	5834	6406	finally
    //   5855	5872	6406	finally
    //   5886	5900	6406	finally
    //   5917	5931	6406	finally
    //   5943	5957	6406	finally
    //   5969	5980	6406	finally
    //   5994	6000	6406	finally
    //   6012	6023	6406	finally
    //   6036	6049	6406	finally
    //   6063	6068	6406	finally
    //   6077	6082	6406	finally
    //   6091	6100	6406	finally
    //   6109	6116	6406	finally
    //   6125	6134	6406	finally
    //   6143	6156	6406	finally
    //   6165	6176	6406	finally
    //   6188	6198	6406	finally
    //   6207	6212	6406	finally
    //   6224	6229	6406	finally
    //   6238	6243	6406	finally
    //   6252	6261	6406	finally
    //   6270	6278	6406	finally
    //   6287	6296	6406	finally
    //   6305	6315	6406	finally
    //   6324	6335	6406	finally
    //   6344	6349	6406	finally
    //   6369	6373	6406	finally
    //   6385	6392	6406	finally
    //   6404	6406	6406	finally
    //   1541	1550	6414	java/io/IOException
    //   1559	1567	6414	java/io/IOException
    //   1576	1585	6414	java/io/IOException
    //   1594	1601	6414	java/io/IOException
    //   1610	1619	6414	java/io/IOException
    //   1628	1641	6414	java/io/IOException
    //   1650	1661	6414	java/io/IOException
    //   1670	1675	6414	java/io/IOException
    //   1690	1697	6414	java/io/IOException
    //   1706	1720	6414	java/io/IOException
    //   1738	1743	6414	java/io/IOException
    //   1752	1757	6414	java/io/IOException
    //   1766	1777	6414	java/io/IOException
    //   1786	1794	6414	java/io/IOException
    //   1803	1808	6414	java/io/IOException
    //   1823	1834	6414	java/io/IOException
    //   1848	1861	6414	java/io/IOException
    //   1870	1883	6414	java/io/IOException
    //   1897	1902	6414	java/io/IOException
    //   1911	1916	6414	java/io/IOException
    //   1925	1934	6414	java/io/IOException
    //   1943	1950	6414	java/io/IOException
    //   1959	1968	6414	java/io/IOException
    //   1977	1990	6414	java/io/IOException
    //   1999	2010	6414	java/io/IOException
    //   2027	2032	6414	java/io/IOException
    //   2041	2046	6414	java/io/IOException
    //   2055	2064	6414	java/io/IOException
    //   2073	2080	6414	java/io/IOException
    //   2089	2098	6414	java/io/IOException
    //   2107	2120	6414	java/io/IOException
    //   2129	2140	6414	java/io/IOException
    //   2152	2164	6414	java/io/IOException
    //   2173	2178	6414	java/io/IOException
    //   2190	2201	6414	java/io/IOException
    //   2215	2228	6414	java/io/IOException
    //   2237	2248	6414	java/io/IOException
    //   2268	2289	6414	java/io/IOException
    //   2303	2308	6414	java/io/IOException
    //   2317	2322	6414	java/io/IOException
    //   2331	2340	6414	java/io/IOException
    //   2349	2356	6414	java/io/IOException
    //   2365	2374	6414	java/io/IOException
    //   2383	2396	6414	java/io/IOException
    //   2405	2416	6414	java/io/IOException
    //   2433	2444	6414	java/io/IOException
    //   2453	2457	6414	java/io/IOException
    //   2469	2477	6414	java/io/IOException
    //   2489	2494	6414	java/io/IOException
    //   2506	2517	6414	java/io/IOException
    //   2531	2544	6414	java/io/IOException
    //   2558	2563	6414	java/io/IOException
    //   2572	2577	6414	java/io/IOException
    //   2586	2595	6414	java/io/IOException
    //   2604	2611	6414	java/io/IOException
    //   2620	2629	6414	java/io/IOException
    //   2638	2651	6414	java/io/IOException
    //   2660	2671	6414	java/io/IOException
    //   2683	2693	6414	java/io/IOException
    //   2702	2707	6414	java/io/IOException
    //   2719	2730	6414	java/io/IOException
    //   2744	2757	6414	java/io/IOException
    //   2771	2776	6414	java/io/IOException
    //   2785	2790	6414	java/io/IOException
    //   2799	2808	6414	java/io/IOException
    //   2817	2824	6414	java/io/IOException
    //   2833	2842	6414	java/io/IOException
    //   2851	2864	6414	java/io/IOException
    //   2873	2884	6414	java/io/IOException
    //   2896	2906	6414	java/io/IOException
    //   2915	2920	6414	java/io/IOException
    //   2932	2943	6414	java/io/IOException
    //   2957	2970	6414	java/io/IOException
    //   2984	2989	6414	java/io/IOException
    //   2998	3003	6414	java/io/IOException
    //   3012	3021	6414	java/io/IOException
    //   3030	3037	6414	java/io/IOException
    //   3046	3055	6414	java/io/IOException
    //   3064	3077	6414	java/io/IOException
    //   3086	3097	6414	java/io/IOException
    //   3109	3119	6414	java/io/IOException
    //   3128	3133	6414	java/io/IOException
    //   3145	3156	6414	java/io/IOException
    //   3170	3183	6414	java/io/IOException
    //   3197	3202	6414	java/io/IOException
    //   3211	3216	6414	java/io/IOException
    //   3225	3234	6414	java/io/IOException
    //   3243	3250	6414	java/io/IOException
    //   3259	3268	6414	java/io/IOException
    //   3277	3290	6414	java/io/IOException
    //   3299	3310	6414	java/io/IOException
    //   3322	3332	6414	java/io/IOException
    //   3341	3346	6414	java/io/IOException
    //   3358	3369	6414	java/io/IOException
    //   3383	3396	6414	java/io/IOException
    //   3410	3415	6414	java/io/IOException
    //   3424	3429	6414	java/io/IOException
    //   3438	3447	6414	java/io/IOException
    //   3456	3463	6414	java/io/IOException
    //   3472	3481	6414	java/io/IOException
    //   3490	3503	6414	java/io/IOException
    //   3512	3523	6414	java/io/IOException
    //   3535	3545	6414	java/io/IOException
    //   3554	3559	6414	java/io/IOException
    //   3571	3582	6414	java/io/IOException
    //   3596	3609	6414	java/io/IOException
    //   3623	3628	6414	java/io/IOException
    //   3637	3642	6414	java/io/IOException
    //   3651	3660	6414	java/io/IOException
    //   3669	3676	6414	java/io/IOException
    //   3685	3694	6414	java/io/IOException
    //   3703	3716	6414	java/io/IOException
    //   3725	3736	6414	java/io/IOException
    //   3748	3758	6414	java/io/IOException
    //   3767	3772	6414	java/io/IOException
    //   3784	3795	6414	java/io/IOException
    //   3809	3822	6414	java/io/IOException
    //   3836	3841	6414	java/io/IOException
    //   3850	3855	6414	java/io/IOException
    //   3864	3873	6414	java/io/IOException
    //   3882	3889	6414	java/io/IOException
    //   3898	3907	6414	java/io/IOException
    //   3916	3929	6414	java/io/IOException
    //   3938	3949	6414	java/io/IOException
    //   3961	3971	6414	java/io/IOException
    //   3980	3985	6414	java/io/IOException
    //   3997	4008	6414	java/io/IOException
    //   4022	4035	6414	java/io/IOException
    //   4049	4054	6414	java/io/IOException
    //   4063	4068	6414	java/io/IOException
    //   4077	4086	6414	java/io/IOException
    //   4095	4102	6414	java/io/IOException
    //   4111	4120	6414	java/io/IOException
    //   4129	4142	6414	java/io/IOException
    //   4151	4162	6414	java/io/IOException
    //   4174	4184	6414	java/io/IOException
    //   4193	4198	6414	java/io/IOException
    //   4210	4221	6414	java/io/IOException
    //   4235	4248	6414	java/io/IOException
    //   4262	4267	6414	java/io/IOException
    //   4276	4281	6414	java/io/IOException
    //   4290	4299	6414	java/io/IOException
    //   4308	4315	6414	java/io/IOException
    //   4324	4333	6414	java/io/IOException
    //   4342	4355	6414	java/io/IOException
    //   4364	4375	6414	java/io/IOException
    //   4387	4397	6414	java/io/IOException
    //   4406	4411	6414	java/io/IOException
    //   4423	4434	6414	java/io/IOException
    //   4448	4461	6414	java/io/IOException
    //   4470	4483	6414	java/io/IOException
    //   4497	4502	6414	java/io/IOException
    //   4511	4516	6414	java/io/IOException
    //   4525	4534	6414	java/io/IOException
    //   4543	4550	6414	java/io/IOException
    //   4559	4568	6414	java/io/IOException
    //   4577	4590	6414	java/io/IOException
    //   4599	4610	6414	java/io/IOException
    //   4627	4632	6414	java/io/IOException
    //   4641	4646	6414	java/io/IOException
    //   4655	4664	6414	java/io/IOException
    //   4673	4680	6414	java/io/IOException
    //   4689	4698	6414	java/io/IOException
    //   4707	4720	6414	java/io/IOException
    //   4729	4740	6414	java/io/IOException
    //   4752	4758	6414	java/io/IOException
    //   4767	4772	6414	java/io/IOException
    //   4781	4790	6414	java/io/IOException
    //   4799	4807	6414	java/io/IOException
    //   4816	4821	6414	java/io/IOException
    //   4833	4844	6414	java/io/IOException
    //   4858	4871	6414	java/io/IOException
    //   4885	4890	6414	java/io/IOException
    //   4899	4904	6414	java/io/IOException
    //   4913	4922	6414	java/io/IOException
    //   4931	4938	6414	java/io/IOException
    //   4947	4956	6414	java/io/IOException
    //   4965	4978	6414	java/io/IOException
    //   4987	4998	6414	java/io/IOException
    //   5010	5017	6414	java/io/IOException
    //   5031	5036	6414	java/io/IOException
    //   5045	5050	6414	java/io/IOException
    //   5059	5068	6414	java/io/IOException
    //   5077	5085	6414	java/io/IOException
    //   5094	5103	6414	java/io/IOException
    //   5112	5119	6414	java/io/IOException
    //   5128	5137	6414	java/io/IOException
    //   5146	5159	6414	java/io/IOException
    //   5168	5179	6414	java/io/IOException
    //   5191	5201	6414	java/io/IOException
    //   5210	5215	6414	java/io/IOException
    //   5227	5238	6414	java/io/IOException
    //   5252	5265	6414	java/io/IOException
    //   5274	5287	6414	java/io/IOException
    //   5309	5323	6414	java/io/IOException
    //   5341	5346	6414	java/io/IOException
    //   5355	5360	6414	java/io/IOException
    //   5369	5381	6414	java/io/IOException
    //   5390	5400	6414	java/io/IOException
    //   5412	5417	6414	java/io/IOException
    //   5426	5431	6414	java/io/IOException
    //   5440	5449	6414	java/io/IOException
    //   5458	5465	6414	java/io/IOException
    //   5474	5483	6414	java/io/IOException
    //   5492	5505	6414	java/io/IOException
    //   5514	5525	6414	java/io/IOException
    //   5534	5539	6414	java/io/IOException
    //   5551	5562	6414	java/io/IOException
    //   5576	5589	6414	java/io/IOException
    //   5603	5608	6414	java/io/IOException
    //   5617	5622	6414	java/io/IOException
    //   5631	5640	6414	java/io/IOException
    //   5649	5656	6414	java/io/IOException
    //   5665	5674	6414	java/io/IOException
    //   5683	5696	6414	java/io/IOException
    //   5705	5716	6414	java/io/IOException
    //   5728	5738	6414	java/io/IOException
    //   5747	5752	6414	java/io/IOException
    //   5764	5775	6414	java/io/IOException
    //   5789	5807	6414	java/io/IOException
    //   5816	5834	6414	java/io/IOException
    //   5855	5872	6414	java/io/IOException
    //   5886	5900	6414	java/io/IOException
    //   5917	5931	6414	java/io/IOException
    //   5943	5957	6414	java/io/IOException
    //   5969	5980	6414	java/io/IOException
    //   5994	6000	6414	java/io/IOException
    //   6012	6023	6414	java/io/IOException
    //   6036	6049	6414	java/io/IOException
    //   6063	6068	6414	java/io/IOException
    //   6077	6082	6414	java/io/IOException
    //   6091	6100	6414	java/io/IOException
    //   6109	6116	6414	java/io/IOException
    //   6125	6134	6414	java/io/IOException
    //   6143	6156	6414	java/io/IOException
    //   6165	6176	6414	java/io/IOException
    //   6188	6198	6414	java/io/IOException
    //   6207	6212	6414	java/io/IOException
    //   6224	6229	6414	java/io/IOException
    //   6238	6243	6414	java/io/IOException
    //   6252	6261	6414	java/io/IOException
    //   6270	6278	6414	java/io/IOException
    //   6287	6296	6414	java/io/IOException
    //   6305	6315	6414	java/io/IOException
    //   6324	6335	6414	java/io/IOException
    //   6344	6349	6414	java/io/IOException
    //   6369	6373	6414	java/io/IOException
    //   6385	6392	6414	java/io/IOException
    //   6404	6406	6414	java/io/IOException
    //   1541	1550	6418	org/xmlpull/v1/XmlPullParserException
    //   1559	1567	6418	org/xmlpull/v1/XmlPullParserException
    //   1576	1585	6418	org/xmlpull/v1/XmlPullParserException
    //   1594	1601	6418	org/xmlpull/v1/XmlPullParserException
    //   1610	1619	6418	org/xmlpull/v1/XmlPullParserException
    //   1628	1641	6418	org/xmlpull/v1/XmlPullParserException
    //   1650	1661	6418	org/xmlpull/v1/XmlPullParserException
    //   1670	1675	6418	org/xmlpull/v1/XmlPullParserException
    //   1690	1697	6418	org/xmlpull/v1/XmlPullParserException
    //   1706	1720	6418	org/xmlpull/v1/XmlPullParserException
    //   1738	1743	6418	org/xmlpull/v1/XmlPullParserException
    //   1752	1757	6418	org/xmlpull/v1/XmlPullParserException
    //   1766	1777	6418	org/xmlpull/v1/XmlPullParserException
    //   1786	1794	6418	org/xmlpull/v1/XmlPullParserException
    //   1803	1808	6418	org/xmlpull/v1/XmlPullParserException
    //   1823	1834	6418	org/xmlpull/v1/XmlPullParserException
    //   1848	1861	6418	org/xmlpull/v1/XmlPullParserException
    //   1870	1883	6418	org/xmlpull/v1/XmlPullParserException
    //   1897	1902	6418	org/xmlpull/v1/XmlPullParserException
    //   1911	1916	6418	org/xmlpull/v1/XmlPullParserException
    //   1925	1934	6418	org/xmlpull/v1/XmlPullParserException
    //   1943	1950	6418	org/xmlpull/v1/XmlPullParserException
    //   1959	1968	6418	org/xmlpull/v1/XmlPullParserException
    //   1977	1990	6418	org/xmlpull/v1/XmlPullParserException
    //   1999	2010	6418	org/xmlpull/v1/XmlPullParserException
    //   2027	2032	6418	org/xmlpull/v1/XmlPullParserException
    //   2041	2046	6418	org/xmlpull/v1/XmlPullParserException
    //   2055	2064	6418	org/xmlpull/v1/XmlPullParserException
    //   2073	2080	6418	org/xmlpull/v1/XmlPullParserException
    //   2089	2098	6418	org/xmlpull/v1/XmlPullParserException
    //   2107	2120	6418	org/xmlpull/v1/XmlPullParserException
    //   2129	2140	6418	org/xmlpull/v1/XmlPullParserException
    //   2152	2164	6418	org/xmlpull/v1/XmlPullParserException
    //   2173	2178	6418	org/xmlpull/v1/XmlPullParserException
    //   2190	2201	6418	org/xmlpull/v1/XmlPullParserException
    //   2215	2228	6418	org/xmlpull/v1/XmlPullParserException
    //   2237	2248	6418	org/xmlpull/v1/XmlPullParserException
    //   2268	2289	6418	org/xmlpull/v1/XmlPullParserException
    //   2303	2308	6418	org/xmlpull/v1/XmlPullParserException
    //   2317	2322	6418	org/xmlpull/v1/XmlPullParserException
    //   2331	2340	6418	org/xmlpull/v1/XmlPullParserException
    //   2349	2356	6418	org/xmlpull/v1/XmlPullParserException
    //   2365	2374	6418	org/xmlpull/v1/XmlPullParserException
    //   2383	2396	6418	org/xmlpull/v1/XmlPullParserException
    //   2405	2416	6418	org/xmlpull/v1/XmlPullParserException
    //   2433	2444	6418	org/xmlpull/v1/XmlPullParserException
    //   2453	2457	6418	org/xmlpull/v1/XmlPullParserException
    //   2469	2477	6418	org/xmlpull/v1/XmlPullParserException
    //   2489	2494	6418	org/xmlpull/v1/XmlPullParserException
    //   2506	2517	6418	org/xmlpull/v1/XmlPullParserException
    //   2531	2544	6418	org/xmlpull/v1/XmlPullParserException
    //   2558	2563	6418	org/xmlpull/v1/XmlPullParserException
    //   2572	2577	6418	org/xmlpull/v1/XmlPullParserException
    //   2586	2595	6418	org/xmlpull/v1/XmlPullParserException
    //   2604	2611	6418	org/xmlpull/v1/XmlPullParserException
    //   2620	2629	6418	org/xmlpull/v1/XmlPullParserException
    //   2638	2651	6418	org/xmlpull/v1/XmlPullParserException
    //   2660	2671	6418	org/xmlpull/v1/XmlPullParserException
    //   2683	2693	6418	org/xmlpull/v1/XmlPullParserException
    //   2702	2707	6418	org/xmlpull/v1/XmlPullParserException
    //   2719	2730	6418	org/xmlpull/v1/XmlPullParserException
    //   2744	2757	6418	org/xmlpull/v1/XmlPullParserException
    //   2771	2776	6418	org/xmlpull/v1/XmlPullParserException
    //   2785	2790	6418	org/xmlpull/v1/XmlPullParserException
    //   2799	2808	6418	org/xmlpull/v1/XmlPullParserException
    //   2817	2824	6418	org/xmlpull/v1/XmlPullParserException
    //   2833	2842	6418	org/xmlpull/v1/XmlPullParserException
    //   2851	2864	6418	org/xmlpull/v1/XmlPullParserException
    //   2873	2884	6418	org/xmlpull/v1/XmlPullParserException
    //   2896	2906	6418	org/xmlpull/v1/XmlPullParserException
    //   2915	2920	6418	org/xmlpull/v1/XmlPullParserException
    //   2932	2943	6418	org/xmlpull/v1/XmlPullParserException
    //   2957	2970	6418	org/xmlpull/v1/XmlPullParserException
    //   2984	2989	6418	org/xmlpull/v1/XmlPullParserException
    //   2998	3003	6418	org/xmlpull/v1/XmlPullParserException
    //   3012	3021	6418	org/xmlpull/v1/XmlPullParserException
    //   3030	3037	6418	org/xmlpull/v1/XmlPullParserException
    //   3046	3055	6418	org/xmlpull/v1/XmlPullParserException
    //   3064	3077	6418	org/xmlpull/v1/XmlPullParserException
    //   3086	3097	6418	org/xmlpull/v1/XmlPullParserException
    //   3109	3119	6418	org/xmlpull/v1/XmlPullParserException
    //   3128	3133	6418	org/xmlpull/v1/XmlPullParserException
    //   3145	3156	6418	org/xmlpull/v1/XmlPullParserException
    //   3170	3183	6418	org/xmlpull/v1/XmlPullParserException
    //   3197	3202	6418	org/xmlpull/v1/XmlPullParserException
    //   3211	3216	6418	org/xmlpull/v1/XmlPullParserException
    //   3225	3234	6418	org/xmlpull/v1/XmlPullParserException
    //   3243	3250	6418	org/xmlpull/v1/XmlPullParserException
    //   3259	3268	6418	org/xmlpull/v1/XmlPullParserException
    //   3277	3290	6418	org/xmlpull/v1/XmlPullParserException
    //   3299	3310	6418	org/xmlpull/v1/XmlPullParserException
    //   3322	3332	6418	org/xmlpull/v1/XmlPullParserException
    //   3341	3346	6418	org/xmlpull/v1/XmlPullParserException
    //   3358	3369	6418	org/xmlpull/v1/XmlPullParserException
    //   3383	3396	6418	org/xmlpull/v1/XmlPullParserException
    //   3410	3415	6418	org/xmlpull/v1/XmlPullParserException
    //   3424	3429	6418	org/xmlpull/v1/XmlPullParserException
    //   3438	3447	6418	org/xmlpull/v1/XmlPullParserException
    //   3456	3463	6418	org/xmlpull/v1/XmlPullParserException
    //   3472	3481	6418	org/xmlpull/v1/XmlPullParserException
    //   3490	3503	6418	org/xmlpull/v1/XmlPullParserException
    //   3512	3523	6418	org/xmlpull/v1/XmlPullParserException
    //   3535	3545	6418	org/xmlpull/v1/XmlPullParserException
    //   3554	3559	6418	org/xmlpull/v1/XmlPullParserException
    //   3571	3582	6418	org/xmlpull/v1/XmlPullParserException
    //   3596	3609	6418	org/xmlpull/v1/XmlPullParserException
    //   3623	3628	6418	org/xmlpull/v1/XmlPullParserException
    //   3637	3642	6418	org/xmlpull/v1/XmlPullParserException
    //   3651	3660	6418	org/xmlpull/v1/XmlPullParserException
    //   3669	3676	6418	org/xmlpull/v1/XmlPullParserException
    //   3685	3694	6418	org/xmlpull/v1/XmlPullParserException
    //   3703	3716	6418	org/xmlpull/v1/XmlPullParserException
    //   3725	3736	6418	org/xmlpull/v1/XmlPullParserException
    //   3748	3758	6418	org/xmlpull/v1/XmlPullParserException
    //   3767	3772	6418	org/xmlpull/v1/XmlPullParserException
    //   3784	3795	6418	org/xmlpull/v1/XmlPullParserException
    //   3809	3822	6418	org/xmlpull/v1/XmlPullParserException
    //   3836	3841	6418	org/xmlpull/v1/XmlPullParserException
    //   3850	3855	6418	org/xmlpull/v1/XmlPullParserException
    //   3864	3873	6418	org/xmlpull/v1/XmlPullParserException
    //   3882	3889	6418	org/xmlpull/v1/XmlPullParserException
    //   3898	3907	6418	org/xmlpull/v1/XmlPullParserException
    //   3916	3929	6418	org/xmlpull/v1/XmlPullParserException
    //   3938	3949	6418	org/xmlpull/v1/XmlPullParserException
    //   3961	3971	6418	org/xmlpull/v1/XmlPullParserException
    //   3980	3985	6418	org/xmlpull/v1/XmlPullParserException
    //   3997	4008	6418	org/xmlpull/v1/XmlPullParserException
    //   4022	4035	6418	org/xmlpull/v1/XmlPullParserException
    //   4049	4054	6418	org/xmlpull/v1/XmlPullParserException
    //   4063	4068	6418	org/xmlpull/v1/XmlPullParserException
    //   4077	4086	6418	org/xmlpull/v1/XmlPullParserException
    //   4095	4102	6418	org/xmlpull/v1/XmlPullParserException
    //   4111	4120	6418	org/xmlpull/v1/XmlPullParserException
    //   4129	4142	6418	org/xmlpull/v1/XmlPullParserException
    //   4151	4162	6418	org/xmlpull/v1/XmlPullParserException
    //   4174	4184	6418	org/xmlpull/v1/XmlPullParserException
    //   4193	4198	6418	org/xmlpull/v1/XmlPullParserException
    //   4210	4221	6418	org/xmlpull/v1/XmlPullParserException
    //   4235	4248	6418	org/xmlpull/v1/XmlPullParserException
    //   4262	4267	6418	org/xmlpull/v1/XmlPullParserException
    //   4276	4281	6418	org/xmlpull/v1/XmlPullParserException
    //   4290	4299	6418	org/xmlpull/v1/XmlPullParserException
    //   4308	4315	6418	org/xmlpull/v1/XmlPullParserException
    //   4324	4333	6418	org/xmlpull/v1/XmlPullParserException
    //   4342	4355	6418	org/xmlpull/v1/XmlPullParserException
    //   4364	4375	6418	org/xmlpull/v1/XmlPullParserException
    //   4387	4397	6418	org/xmlpull/v1/XmlPullParserException
    //   4406	4411	6418	org/xmlpull/v1/XmlPullParserException
    //   4423	4434	6418	org/xmlpull/v1/XmlPullParserException
    //   4448	4461	6418	org/xmlpull/v1/XmlPullParserException
    //   4470	4483	6418	org/xmlpull/v1/XmlPullParserException
    //   4497	4502	6418	org/xmlpull/v1/XmlPullParserException
    //   4511	4516	6418	org/xmlpull/v1/XmlPullParserException
    //   4525	4534	6418	org/xmlpull/v1/XmlPullParserException
    //   4543	4550	6418	org/xmlpull/v1/XmlPullParserException
    //   4559	4568	6418	org/xmlpull/v1/XmlPullParserException
    //   4577	4590	6418	org/xmlpull/v1/XmlPullParserException
    //   4599	4610	6418	org/xmlpull/v1/XmlPullParserException
    //   4627	4632	6418	org/xmlpull/v1/XmlPullParserException
    //   4641	4646	6418	org/xmlpull/v1/XmlPullParserException
    //   4655	4664	6418	org/xmlpull/v1/XmlPullParserException
    //   4673	4680	6418	org/xmlpull/v1/XmlPullParserException
    //   4689	4698	6418	org/xmlpull/v1/XmlPullParserException
    //   4707	4720	6418	org/xmlpull/v1/XmlPullParserException
    //   4729	4740	6418	org/xmlpull/v1/XmlPullParserException
    //   4752	4758	6418	org/xmlpull/v1/XmlPullParserException
    //   4767	4772	6418	org/xmlpull/v1/XmlPullParserException
    //   4781	4790	6418	org/xmlpull/v1/XmlPullParserException
    //   4799	4807	6418	org/xmlpull/v1/XmlPullParserException
    //   4816	4821	6418	org/xmlpull/v1/XmlPullParserException
    //   4833	4844	6418	org/xmlpull/v1/XmlPullParserException
    //   4858	4871	6418	org/xmlpull/v1/XmlPullParserException
    //   4885	4890	6418	org/xmlpull/v1/XmlPullParserException
    //   4899	4904	6418	org/xmlpull/v1/XmlPullParserException
    //   4913	4922	6418	org/xmlpull/v1/XmlPullParserException
    //   4931	4938	6418	org/xmlpull/v1/XmlPullParserException
    //   4947	4956	6418	org/xmlpull/v1/XmlPullParserException
    //   4965	4978	6418	org/xmlpull/v1/XmlPullParserException
    //   4987	4998	6418	org/xmlpull/v1/XmlPullParserException
    //   5010	5017	6418	org/xmlpull/v1/XmlPullParserException
    //   5031	5036	6418	org/xmlpull/v1/XmlPullParserException
    //   5045	5050	6418	org/xmlpull/v1/XmlPullParserException
    //   5059	5068	6418	org/xmlpull/v1/XmlPullParserException
    //   5077	5085	6418	org/xmlpull/v1/XmlPullParserException
    //   5094	5103	6418	org/xmlpull/v1/XmlPullParserException
    //   5112	5119	6418	org/xmlpull/v1/XmlPullParserException
    //   5128	5137	6418	org/xmlpull/v1/XmlPullParserException
    //   5146	5159	6418	org/xmlpull/v1/XmlPullParserException
    //   5168	5179	6418	org/xmlpull/v1/XmlPullParserException
    //   5191	5201	6418	org/xmlpull/v1/XmlPullParserException
    //   5210	5215	6418	org/xmlpull/v1/XmlPullParserException
    //   5227	5238	6418	org/xmlpull/v1/XmlPullParserException
    //   5252	5265	6418	org/xmlpull/v1/XmlPullParserException
    //   5274	5287	6418	org/xmlpull/v1/XmlPullParserException
    //   5309	5323	6418	org/xmlpull/v1/XmlPullParserException
    //   5341	5346	6418	org/xmlpull/v1/XmlPullParserException
    //   5355	5360	6418	org/xmlpull/v1/XmlPullParserException
    //   5369	5381	6418	org/xmlpull/v1/XmlPullParserException
    //   5390	5400	6418	org/xmlpull/v1/XmlPullParserException
    //   5412	5417	6418	org/xmlpull/v1/XmlPullParserException
    //   5426	5431	6418	org/xmlpull/v1/XmlPullParserException
    //   5440	5449	6418	org/xmlpull/v1/XmlPullParserException
    //   5458	5465	6418	org/xmlpull/v1/XmlPullParserException
    //   5474	5483	6418	org/xmlpull/v1/XmlPullParserException
    //   5492	5505	6418	org/xmlpull/v1/XmlPullParserException
    //   5514	5525	6418	org/xmlpull/v1/XmlPullParserException
    //   5534	5539	6418	org/xmlpull/v1/XmlPullParserException
    //   5551	5562	6418	org/xmlpull/v1/XmlPullParserException
    //   5576	5589	6418	org/xmlpull/v1/XmlPullParserException
    //   5603	5608	6418	org/xmlpull/v1/XmlPullParserException
    //   5617	5622	6418	org/xmlpull/v1/XmlPullParserException
    //   5631	5640	6418	org/xmlpull/v1/XmlPullParserException
    //   5649	5656	6418	org/xmlpull/v1/XmlPullParserException
    //   5665	5674	6418	org/xmlpull/v1/XmlPullParserException
    //   5683	5696	6418	org/xmlpull/v1/XmlPullParserException
    //   5705	5716	6418	org/xmlpull/v1/XmlPullParserException
    //   5728	5738	6418	org/xmlpull/v1/XmlPullParserException
    //   5747	5752	6418	org/xmlpull/v1/XmlPullParserException
    //   5764	5775	6418	org/xmlpull/v1/XmlPullParserException
    //   5789	5807	6418	org/xmlpull/v1/XmlPullParserException
    //   5816	5834	6418	org/xmlpull/v1/XmlPullParserException
    //   5855	5872	6418	org/xmlpull/v1/XmlPullParserException
    //   5886	5900	6418	org/xmlpull/v1/XmlPullParserException
    //   5917	5931	6418	org/xmlpull/v1/XmlPullParserException
    //   5943	5957	6418	org/xmlpull/v1/XmlPullParserException
    //   5969	5980	6418	org/xmlpull/v1/XmlPullParserException
    //   5994	6000	6418	org/xmlpull/v1/XmlPullParserException
    //   6012	6023	6418	org/xmlpull/v1/XmlPullParserException
    //   6036	6049	6418	org/xmlpull/v1/XmlPullParserException
    //   6063	6068	6418	org/xmlpull/v1/XmlPullParserException
    //   6077	6082	6418	org/xmlpull/v1/XmlPullParserException
    //   6091	6100	6418	org/xmlpull/v1/XmlPullParserException
    //   6109	6116	6418	org/xmlpull/v1/XmlPullParserException
    //   6125	6134	6418	org/xmlpull/v1/XmlPullParserException
    //   6143	6156	6418	org/xmlpull/v1/XmlPullParserException
    //   6165	6176	6418	org/xmlpull/v1/XmlPullParserException
    //   6188	6198	6418	org/xmlpull/v1/XmlPullParserException
    //   6207	6212	6418	org/xmlpull/v1/XmlPullParserException
    //   6224	6229	6418	org/xmlpull/v1/XmlPullParserException
    //   6238	6243	6418	org/xmlpull/v1/XmlPullParserException
    //   6252	6261	6418	org/xmlpull/v1/XmlPullParserException
    //   6270	6278	6418	org/xmlpull/v1/XmlPullParserException
    //   6287	6296	6418	org/xmlpull/v1/XmlPullParserException
    //   6305	6315	6418	org/xmlpull/v1/XmlPullParserException
    //   6324	6335	6418	org/xmlpull/v1/XmlPullParserException
    //   6344	6349	6418	org/xmlpull/v1/XmlPullParserException
    //   6369	6373	6418	org/xmlpull/v1/XmlPullParserException
    //   6385	6392	6418	org/xmlpull/v1/XmlPullParserException
    //   6404	6406	6418	org/xmlpull/v1/XmlPullParserException
    //   42	51	6426	org/xmlpull/v1/XmlPullParserException
    //   63	72	6426	org/xmlpull/v1/XmlPullParserException
    //   112	126	6426	org/xmlpull/v1/XmlPullParserException
    //   506	511	6426	org/xmlpull/v1/XmlPullParserException
    //   523	532	6426	org/xmlpull/v1/XmlPullParserException
    //   559	568	6426	org/xmlpull/v1/XmlPullParserException
    //   580	590	6426	org/xmlpull/v1/XmlPullParserException
    //   842	852	6426	org/xmlpull/v1/XmlPullParserException
    //   1083	1094	6426	org/xmlpull/v1/XmlPullParserException
    //   1111	1124	6426	org/xmlpull/v1/XmlPullParserException
    //   1297	1310	6426	org/xmlpull/v1/XmlPullParserException
    //   1483	1490	6426	org/xmlpull/v1/XmlPullParserException
    //   1507	1512	6426	org/xmlpull/v1/XmlPullParserException
    //   1524	1529	6426	org/xmlpull/v1/XmlPullParserException
    //   25	30	6434	finally
    //   42	51	6434	finally
    //   63	72	6434	finally
    //   112	126	6434	finally
    //   506	511	6434	finally
    //   523	532	6434	finally
    //   559	568	6434	finally
    //   580	590	6434	finally
    //   842	852	6434	finally
    //   1083	1094	6434	finally
    //   1111	1124	6434	finally
    //   1297	1310	6434	finally
    //   1483	1490	6434	finally
    //   1507	1512	6434	finally
    //   1524	1529	6434	finally
    //   25	30	6442	java/io/IOException
    //   42	51	6442	java/io/IOException
    //   63	72	6442	java/io/IOException
    //   112	126	6442	java/io/IOException
    //   506	511	6442	java/io/IOException
    //   523	532	6442	java/io/IOException
    //   559	568	6442	java/io/IOException
    //   580	590	6442	java/io/IOException
    //   842	852	6442	java/io/IOException
    //   1083	1094	6442	java/io/IOException
    //   1111	1124	6442	java/io/IOException
    //   1297	1310	6442	java/io/IOException
    //   1483	1490	6442	java/io/IOException
    //   1507	1512	6442	java/io/IOException
    //   1524	1529	6442	java/io/IOException
    //   6447	6457	6465	finally
    //   25	30	6473	org/xmlpull/v1/XmlPullParserException
    //   6482	6493	6595	finally
    //   2	12	6610	java/io/FileNotFoundException
  }
  
  private void readPrivAppPermissions(XmlPullParser paramXmlPullParser, ArrayMap<String, ArraySet<String>> paramArrayMap1, ArrayMap<String, ArraySet<String>> paramArrayMap2)
    throws IOException, XmlPullParserException
  {
    String str1 = paramXmlPullParser.getAttributeValue(null, "package");
    if (TextUtils.isEmpty(str1))
    {
      paramArrayMap1 = new StringBuilder();
      paramArrayMap1.append("package is required for <privapp-permissions> in ");
      paramArrayMap1.append(paramXmlPullParser.getPositionDescription());
      Slog.w("SystemConfig", paramArrayMap1.toString());
      return;
    }
    Object localObject1 = (ArraySet)paramArrayMap1.get(str1);
    Object localObject2 = localObject1;
    if (localObject1 == null) {
      localObject2 = new ArraySet();
    }
    localObject1 = (ArraySet)paramArrayMap2.get(str1);
    int i = paramXmlPullParser.getDepth();
    while (XmlUtils.nextElementWithin(paramXmlPullParser, i))
    {
      String str2 = paramXmlPullParser.getName();
      Object localObject3;
      if ("permission".equals(str2))
      {
        localObject3 = paramXmlPullParser.getAttributeValue(null, "name");
        if (TextUtils.isEmpty((CharSequence)localObject3))
        {
          localObject3 = new StringBuilder();
          ((StringBuilder)localObject3).append("name is required for <permission> in ");
          ((StringBuilder)localObject3).append(paramXmlPullParser.getPositionDescription());
          Slog.w("SystemConfig", ((StringBuilder)localObject3).toString());
          continue;
        }
        ((ArraySet)localObject2).add(localObject3);
        localObject3 = localObject1;
      }
      else
      {
        localObject3 = localObject1;
        if ("deny-permission".equals(str2))
        {
          str2 = paramXmlPullParser.getAttributeValue(null, "name");
          if (TextUtils.isEmpty(str2))
          {
            localObject3 = new StringBuilder();
            ((StringBuilder)localObject3).append("name is required for <deny-permission> in ");
            ((StringBuilder)localObject3).append(paramXmlPullParser.getPositionDescription());
            Slog.w("SystemConfig", ((StringBuilder)localObject3).toString());
            continue;
          }
          localObject3 = localObject1;
          if (localObject1 == null) {
            localObject3 = new ArraySet();
          }
          ((ArraySet)localObject3).add(str2);
        }
      }
      localObject1 = localObject3;
    }
    paramArrayMap1.put(str1, localObject2);
    if (localObject1 != null) {
      paramArrayMap2.put(str1, localObject1);
    }
  }
  
  private void removeFeature(String paramString)
  {
    if (mAvailableFeatures.remove(paramString) != null)
    {
      StringBuilder localStringBuilder = new StringBuilder();
      localStringBuilder.append("Removed unavailable feature ");
      localStringBuilder.append(paramString);
      Slog.d("SystemConfig", localStringBuilder.toString());
    }
  }
  
  public ArraySet<String> getAllowImplicitBroadcasts()
  {
    return mAllowImplicitBroadcasts;
  }
  
  public ArraySet<String> getAllowInDataUsageSave()
  {
    return mAllowInDataUsageSave;
  }
  
  public ArraySet<String> getAllowInPowerSave()
  {
    return mAllowInPowerSave;
  }
  
  public ArraySet<String> getAllowInPowerSaveExceptIdle()
  {
    return mAllowInPowerSaveExceptIdle;
  }
  
  public ArraySet<String> getAllowUnthrottledLocation()
  {
    return mAllowUnthrottledLocation;
  }
  
  public ArrayMap<String, FeatureInfo> getAvailableFeatures()
  {
    return mAvailableFeatures;
  }
  
  public ArraySet<ComponentName> getBackupTransportWhitelist()
  {
    return mBackupTransportWhitelist;
  }
  
  public ArraySet<ComponentName> getDefaultVrComponents()
  {
    return mDefaultVrComponents;
  }
  
  public ArraySet<String> getDisabledUntilUsedPreinstalledCarrierApps()
  {
    return mDisabledUntilUsedPreinstalledCarrierApps;
  }
  
  public ArrayMap<String, List<String>> getDisabledUntilUsedPreinstalledCarrierAssociatedApps()
  {
    return mDisabledUntilUsedPreinstalledCarrierAssociatedApps;
  }
  
  public int[] getGlobalGids()
  {
    return mGlobalGids;
  }
  
  public ArraySet<String> getHiddenApiWhitelistedApps()
  {
    return mHiddenApiPackageWhitelist;
  }
  
  public ArraySet<String> getLinkedApps()
  {
    return mLinkedApps;
  }
  
  public Map<String, Boolean> getOemPermissions(String paramString)
  {
    paramString = (Map)mOemPermissions.get(paramString);
    if (paramString != null) {
      return paramString;
    }
    return Collections.emptyMap();
  }
  
  public ArrayMap<String, PermissionEntry> getPermissions()
  {
    return mPermissions;
  }
  
  public ArraySet<String> getPrivAppDenyPermissions(String paramString)
  {
    return (ArraySet)mPrivAppDenyPermissions.get(paramString);
  }
  
  public ArraySet<String> getPrivAppPermissions(String paramString)
  {
    return (ArraySet)mPrivAppPermissions.get(paramString);
  }
  
  public ArraySet<String> getProductPrivAppDenyPermissions(String paramString)
  {
    return (ArraySet)mProductPrivAppDenyPermissions.get(paramString);
  }
  
  public ArraySet<String> getProductPrivAppPermissions(String paramString)
  {
    return (ArraySet)mProductPrivAppPermissions.get(paramString);
  }
  
  public ArrayMap<String, String> getSharedLibraries()
  {
    return mSharedLibraries;
  }
  
  public SparseArray<ArraySet<String>> getSystemPermissions()
  {
    return mSystemPermissions;
  }
  
  public ArraySet<String> getSystemUserBlacklistedApps()
  {
    return mSystemUserBlacklistedApps;
  }
  
  public ArraySet<String> getSystemUserWhitelistedApps()
  {
    return mSystemUserWhitelistedApps;
  }
  
  public ArraySet<String> getVendorPrivAppDenyPermissions(String paramString)
  {
    return (ArraySet)mVendorPrivAppDenyPermissions.get(paramString);
  }
  
  public ArraySet<String> getVendorPrivAppPermissions(String paramString)
  {
    return (ArraySet)mVendorPrivAppPermissions.get(paramString);
  }
  
  void readOemPermissions(XmlPullParser paramXmlPullParser)
    throws IOException, XmlPullParserException
  {
    String str = paramXmlPullParser.getAttributeValue(null, "package");
    if (TextUtils.isEmpty(str))
    {
      localObject1 = new StringBuilder();
      ((StringBuilder)localObject1).append("package is required for <oem-permissions> in ");
      ((StringBuilder)localObject1).append(paramXmlPullParser.getPositionDescription());
      Slog.w("SystemConfig", ((StringBuilder)localObject1).toString());
      return;
    }
    Object localObject2 = (ArrayMap)mOemPermissions.get(str);
    Object localObject1 = localObject2;
    if (localObject2 == null) {
      localObject1 = new ArrayMap();
    }
    int i = paramXmlPullParser.getDepth();
    while (XmlUtils.nextElementWithin(paramXmlPullParser, i))
    {
      localObject2 = paramXmlPullParser.getName();
      if ("permission".equals(localObject2))
      {
        localObject2 = paramXmlPullParser.getAttributeValue(null, "name");
        if (TextUtils.isEmpty((CharSequence)localObject2))
        {
          localObject2 = new StringBuilder();
          ((StringBuilder)localObject2).append("name is required for <permission> in ");
          ((StringBuilder)localObject2).append(paramXmlPullParser.getPositionDescription());
          Slog.w("SystemConfig", ((StringBuilder)localObject2).toString());
        }
        else
        {
          ((ArrayMap)localObject1).put(localObject2, Boolean.TRUE);
        }
      }
      else if ("deny-permission".equals(localObject2))
      {
        localObject2 = paramXmlPullParser.getAttributeValue(null, "name");
        if (TextUtils.isEmpty((CharSequence)localObject2))
        {
          localObject2 = new StringBuilder();
          ((StringBuilder)localObject2).append("name is required for <deny-permission> in ");
          ((StringBuilder)localObject2).append(paramXmlPullParser.getPositionDescription());
          Slog.w("SystemConfig", ((StringBuilder)localObject2).toString());
        }
        else
        {
          ((ArrayMap)localObject1).put(localObject2, Boolean.FALSE);
        }
      }
    }
    mOemPermissions.put(str, localObject1);
  }
  
  void readPermission(XmlPullParser paramXmlPullParser, String paramString)
    throws IOException, XmlPullParserException
  {
    if (!mPermissions.containsKey(paramString))
    {
      PermissionEntry localPermissionEntry = new PermissionEntry(paramString, XmlUtils.readBooleanAttribute(paramXmlPullParser, "perUser", false));
      mPermissions.put(paramString, localPermissionEntry);
      int i = paramXmlPullParser.getDepth();
      for (;;)
      {
        int j = paramXmlPullParser.next();
        if ((j == 1) || ((j == 3) && (paramXmlPullParser.getDepth() <= i))) {
          break;
        }
        if ((j != 3) && (j != 4))
        {
          if ("group".equals(paramXmlPullParser.getName()))
          {
            paramString = paramXmlPullParser.getAttributeValue(null, "gid");
            if (paramString != null)
            {
              j = Process.getGidForName(paramString);
              gids = ArrayUtils.appendInt(gids, j);
            }
            else
            {
              paramString = new StringBuilder();
              paramString.append("<group> without gid at ");
              paramString.append(paramXmlPullParser.getPositionDescription());
              Slog.w("SystemConfig", paramString.toString());
            }
          }
          XmlUtils.skipCurrentTag(paramXmlPullParser);
        }
      }
      return;
    }
    paramXmlPullParser = new StringBuilder();
    paramXmlPullParser.append("Duplicate permission definition for ");
    paramXmlPullParser.append(paramString);
    throw new IllegalStateException(paramXmlPullParser.toString());
  }
  
  void readPermissions(File paramFile, int paramInt)
  {
    Object localObject;
    if ((paramFile.exists()) && (paramFile.isDirectory()))
    {
      if (!paramFile.canRead())
      {
        localObject = new StringBuilder();
        ((StringBuilder)localObject).append("Directory ");
        ((StringBuilder)localObject).append(paramFile);
        ((StringBuilder)localObject).append(" cannot be read");
        Slog.w("SystemConfig", ((StringBuilder)localObject).toString());
        return;
      }
      localObject = null;
      for (File localFile : paramFile.listFiles()) {
        if (localFile.getPath().endsWith("etc/permissions/platform.xml"))
        {
          localObject = localFile;
        }
        else
        {
          StringBuilder localStringBuilder;
          if (!localFile.getPath().endsWith(".xml"))
          {
            localStringBuilder = new StringBuilder();
            localStringBuilder.append("Non-xml file ");
            localStringBuilder.append(localFile);
            localStringBuilder.append(" in ");
            localStringBuilder.append(paramFile);
            localStringBuilder.append(" directory, ignoring");
            Slog.i("SystemConfig", localStringBuilder.toString());
          }
          else if (!localFile.canRead())
          {
            localStringBuilder = new StringBuilder();
            localStringBuilder.append("Permissions library file ");
            localStringBuilder.append(localFile);
            localStringBuilder.append(" cannot be read");
            Slog.w("SystemConfig", localStringBuilder.toString());
          }
          else
          {
            readPermissionsFromXml(localFile, paramInt);
          }
        }
      }
      if (localObject != null) {
        readPermissionsFromXml((File)localObject, paramInt);
      }
      return;
    }
    if (paramInt == -1)
    {
      localObject = new StringBuilder();
      ((StringBuilder)localObject).append("No directory ");
      ((StringBuilder)localObject).append(paramFile);
      ((StringBuilder)localObject).append(", skipping");
      Slog.w("SystemConfig", ((StringBuilder)localObject).toString());
    }
  }
  
  public static final class PermissionEntry
  {
    public int[] gids;
    public final String name;
    public boolean perUser;
    
    PermissionEntry(String paramString, boolean paramBoolean)
    {
      name = paramString;
      perUser = paramBoolean;
    }
  }
}
